{
  "date": "2026-07-14",
  "run_label": "Live 14:47 IST",
  "run_time": "09:26",
  "results": {
    "\u20b90\u2013\u20b9500": [
      {
        "Price_Band": "\u20b90\u2013\u20b9500",
        "Stock": "GPIL.NS",
        "Company_Name": "Godawari Power & Ispat Limited",
        "Buy_Price": 251.25,
        "Exit_Target": 307.56,
        "Gross_ROI_%": 20.01,
        "After_Tax_ROI_%": 19.79,
        "Tax_Type": "LTCG",
        "Min_Hold_Until": "01 Jul 2027",
        "Best_Sell_Date": "03 Jan 2028",
        "Forecast_Expires": "03 Jan 2028",
        "Avg_Daily_Turnover_Cr": 32.54,
        "Sector": "Basic Materials",
        "Liquidity": "High",
        "Data_Days": 742,
        "Predicted_Best_Buy_Date": "17 Jul 2026",
        "Predicted_Best_Buy_Price": 248.67,
        "Fundamental_Risk": "Low",
        "Risk_Score": 7,
        "Risk_Reasons": "PE=20.0 within limit=55 (1.0\u00d7); D/E=0.08 within limit=3.25 (1.0\u00d7); Revenue growth=9.7% \u2192 0.90\u00d7; All 3 fields present (1.0\u00d7); ROE=14.9% \u2014 adequate (1.0\u00d7); EV/EBITDA=12.0x within limit=22x (1.0\u00d7); Earnings quality=1.45 \u2014 adequate (1.0\u00d7); Net Debt/EBITDA=-0.6x \u2014 net cash position (0.95\u00d7)"
      },
      {
        "Price_Band": "\u20b90\u2013\u20b9500",
        "Stock": "TMCV.NS",
        "Company_Name": "TATA MOTORS LIMITED",
        "Buy_Price": 416.75,
        "Exit_Target": 476.54,
        "Gross_ROI_%": 12.11,
        "After_Tax_ROI_%": 11.89,
        "Tax_Type": "LTCG",
        "Min_Hold_Until": "01 Jul 2027",
        "Best_Sell_Date": "20 Oct 2027",
        "Forecast_Expires": "20 Oct 2027",
        "Avg_Daily_Turnover_Cr": 338.53,
        "Sector": "Consumer Cyclical",
        "Liquidity": "High",
        "Data_Days": 168,
        "Predicted_Best_Buy_Date": "23 Jul 2026",
        "Predicted_Best_Buy_Price": 415.1,
        "Fundamental_Risk": "High",
        "Risk_Score": 84,
        "Risk_Reasons": "PE=50.8 vs limit=25 \u2192 2.03\u00d7 (4.00\u00d7); D/E=0.44 within limit=2.55 (1.0\u00d7); Revenue growth=-37.8% \u2192 2.20\u00d7; All 3 fields present (1.0\u00d7); ROE=26.0% \u2014 strong (0.90\u00d7); EV/EBITDA=17.4x within limit=18x (1.0\u00d7); Earnings quality=4.94 \u2014 adequate (1.0\u00d7); Net Debt/EBITDA=-0.9x \u2014 net cash position (0.95\u00d7)"
      },
      {
        "Price_Band": "\u20b90\u2013\u20b9500",
        "Stock": "MAHABANK.NS",
        "Company_Name": "Bank of Maharashtra",
        "Buy_Price": 79.45,
        "Exit_Target": 88.37,
        "Gross_ROI_%": 9.05,
        "After_Tax_ROI_%": 8.84,
        "Tax_Type": "LTCG",
        "Min_Hold_Until": "01 Jul 2027",
        "Best_Sell_Date": "26 Apr 2028",
        "Forecast_Expires": "19 Jun 2028",
        "Avg_Daily_Turnover_Cr": 172.11,
        "Sector": "Financial Services",
        "Liquidity": "High",
        "Data_Days": 742,
        "Predicted_Best_Buy_Date": "15 Jul 2026",
        "Predicted_Best_Buy_Price": 79.46,
        "Fundamental_Risk": "Low",
        "Risk_Score": 13,
        "Risk_Reasons": "PE=8.3 within limit=22 (1.0\u00d7); D/E exempt \u2014 financial sector (1.0\u00d7); Revenue growth=21.8% \u2192 0.85\u00d7; 1 field(s) missing \u2192 1.2\u00d7; ROE=23.0% \u2014 acceptable (1.0\u00d7); EV/EBITDA unavailable \u2014 no multiplier; Earnings quality unavailable \u2014 no multiplier; Net Debt/EBITDA unavailable \u2014 no multiplier"
      },
      {
        "Price_Band": "\u20b90\u2013\u20b9500",
        "Stock": "JINDALSAW.NS",
        "Company_Name": "Jindal Saw Limited",
        "Buy_Price": 267.3,
        "Exit_Target": 297.33,
        "Gross_ROI_%": 9.05,
        "After_Tax_ROI_%": 8.84,
        "Tax_Type": "LTCG",
        "Min_Hold_Until": "01 Jul 2027",
        "Best_Sell_Date": "12 Jun 2028",
        "Forecast_Expires": "19 Jun 2028",
        "Avg_Daily_Turnover_Cr": 46.58,
        "Sector": "Basic Materials",
        "Liquidity": "High",
        "Data_Days": 742,
        "Predicted_Best_Buy_Date": "21 Jul 2026",
        "Predicted_Best_Buy_Price": 267.83,
        "Fundamental_Risk": "Medium",
        "Risk_Score": 37,
        "Risk_Reasons": "PE=17.6 within limit=55 (1.0\u00d7); D/E=0.38 within limit=3.25 (1.0\u00d7); Revenue growth=-8.2% \u2192 1.58\u00d7; All 3 fields present (1.0\u00d7); ROE=8.0% \u2014 poor capital allocation (1.27\u00d7); EV/EBITDA=9.7x within limit=22x (1.0\u00d7); Earnings quality=1.82 \u2014 adequate (1.0\u00d7); Net Debt/EBITDA=1.9x within limit=3.5x (1.0\u00d7)"
      },
      {
        "Price_Band": "\u20b90\u2013\u20b9500",
        "Stock": "THELEELA.NS",
        "Company_Name": "Leela Palaces Hotels & Resorts Limited",
        "Buy_Price": 491.45,
        "Exit_Target": 546.38,
        "Gross_ROI_%": 9.0,
        "After_Tax_ROI_%": 8.79,
        "Tax_Type": "LTCG",
        "Min_Hold_Until": "01 Jul 2027",
        "Best_Sell_Date": "12 Jun 2028",
        "Forecast_Expires": "19 Jun 2028",
        "Avg_Daily_Turnover_Cr": 27.64,
        "Sector": "Consumer Cyclical",
        "Liquidity": "High",
        "Data_Days": 279,
        "Predicted_Best_Buy_Date": "15 Jul 2026",
        "Predicted_Best_Buy_Price": 492.11,
        "Fundamental_Risk": "Low",
        "Risk_Score": 29,
        "Risk_Reasons": "PE=39.6 within limit=78 (1.0\u00d7); D/E=0.28 within limit=2.55 (1.0\u00d7); Revenue growth=8.2% \u2192 0.92\u00d7; All 3 fields present (1.0\u00d7); ROE=8.0% \u2014 poor capital allocation (1.26\u00d7); EV/EBITDA=24.4x vs limit=18x (1.39\u00d7); Earnings quality=1.93 \u2014 adequate (1.0\u00d7); Net Debt/EBITDA=2.0x within limit=3.5x (1.0\u00d7)"
      },
      {
        "Price_Band": "\u20b90\u2013\u20b9500",
        "Stock": "NLCINDIA.NS",
        "Company_Name": "NLC India Limited",
        "Buy_Price": 303.55,
        "Exit_Target": 337.38,
        "Gross_ROI_%": 8.97,
        "After_Tax_ROI_%": 8.76,
        "Tax_Type": "LTCG",
        "Min_Hold_Until": "01 Jul 2027",
        "Best_Sell_Date": "16 May 2028",
        "Forecast_Expires": "19 Jun 2028",
        "Avg_Daily_Turnover_Cr": 109.29,
        "Sector": "Utilities",
        "Liquidity": "High",
        "Data_Days": 742,
        "Predicted_Best_Buy_Date": "15 Jul 2026",
        "Predicted_Best_Buy_Price": 303.6,
        "Fundamental_Risk": "Low",
        "Risk_Score": 13,
        "Risk_Reasons": "PE=12.3 within limit=38 (1.0\u00d7); D/E=0.82 within limit=5.5 (1.0\u00d7); Revenue growth=-0.3% \u2192 1.01\u00d7; All 3 fields present (1.0\u00d7); ROE=16.0% \u2014 acceptable for utility (1.0\u00d7); EV/EBITDA=9.7x within limit=22x (1.0\u00d7); Earnings quality=1.47 \u2014 adequate (1.0\u00d7); Net Debt/EBITDA=2.0x within limit=6.0x (1.0\u00d7)"
      },
      {
        "Price_Band": "\u20b90\u2013\u20b9500",
        "Stock": "HINDCOPPER.NS",
        "Company_Name": "Hindustan Copper Limited",
        "Buy_Price": 490.0,
        "Exit_Target": 543.6,
        "Gross_ROI_%": 8.76,
        "After_Tax_ROI_%": 8.56,
        "Tax_Type": "LTCG",
        "Min_Hold_Until": "01 Jul 2027",
        "Best_Sell_Date": "15 Jul 2027",
        "Forecast_Expires": "06 Sep 2027",
        "Avg_Daily_Turnover_Cr": 169.02,
        "Sector": "Basic Materials",
        "Liquidity": "High",
        "Data_Days": 742,
        "Predicted_Best_Buy_Date": "25 Aug 2026",
        "Predicted_Best_Buy_Price": 487.12,
        "Fundamental_Risk": "Low",
        "Risk_Score": 17,
        "Risk_Reasons": "PE=51.5 within limit=55 (1.0\u00d7); D/E=0.03 within limit=3.25 (1.0\u00d7); Revenue growth=58.1% \u2192 0.85\u00d7; All 3 fields present (1.0\u00d7); ROE=30.6% \u2014 strong (0.90\u00d7); EV/EBITDA=32.5x vs limit=22x (1.57\u00d7); Earnings quality=1.60 \u2014 adequate (1.0\u00d7); Net Debt/EBITDA=-0.5x \u2014 net cash position (0.95\u00d7)"
      },
      {
        "Price_Band": "\u20b90\u2013\u20b9500",
        "Stock": "IFCI.NS",
        "Company_Name": "IFCI Limited",
        "Buy_Price": 74.56,
        "Exit_Target": 82.65,
        "Gross_ROI_%": 8.68,
        "After_Tax_ROI_%": 8.47,
        "Tax_Type": "LTCG",
        "Min_Hold_Until": "01 Jul 2027",
        "Best_Sell_Date": "09 Feb 2028",
        "Forecast_Expires": "20 Mar 2028",
        "Avg_Daily_Turnover_Cr": 554.38,
        "Sector": "Financial Services",
        "Liquidity": "High",
        "Data_Days": 742,
        "Predicted_Best_Buy_Date": "15 Jul 2026",
        "Predicted_Best_Buy_Price": 74.61,
        "Fundamental_Risk": "High",
        "Risk_Score": 76,
        "Risk_Reasons": "PE=109.6 vs limit=45 \u2192 2.44\u00d7 (4.00\u00d7); D/E exempt \u2014 financial sector (1.0\u00d7); Revenue growth unavailable \u2014 no multiplier; 2 field(s) missing \u2192 1.5\u00d7; ROE unavailable \u2014 no multiplier; EV/EBITDA unavailable \u2014 no multiplier; Earnings quality unavailable \u2014 no multiplier; Net Debt/EBITDA unavailable \u2014 no multiplier"
      }
    ],
    "\u20b9500\u2013\u20b91000": [
      {
        "Price_Band": "\u20b9500\u2013\u20b91000",
        "Stock": "NATCOPHARM.NS",
        "Company_Name": "NATCO Pharma Limited",
        "Buy_Price": 970.2,
        "Exit_Target": 1181.36,
        "Gross_ROI_%": 19.38,
        "After_Tax_ROI_%": 19.16,
        "Tax_Type": "LTCG",
        "Min_Hold_Until": "01 Jul 2027",
        "Best_Sell_Date": "01 Oct 2027",
        "Forecast_Expires": "01 Oct 2027",
        "Avg_Daily_Turnover_Cr": 64.53,
        "Sector": "Healthcare",
        "Liquidity": "High",
        "Data_Days": 742,
        "Predicted_Best_Buy_Date": "15 Jul 2026",
        "Predicted_Best_Buy_Price": 972.53,
        "Fundamental_Risk": "Medium",
        "Risk_Score": 38,
        "Risk_Reasons": "PE=12.2 within limit=50 (1.0\u00d7); D/E=0.08 within limit=2.75 (1.0\u00d7); Revenue growth=-39.6% \u2192 2.20\u00d7; All 3 fields present (1.0\u00d7); ROE=16.9% \u2014 adequate (1.0\u00d7); EV/EBITDA=11.2x within limit=25x (1.0\u00d7); Earnings quality=1.25 \u2014 adequate (1.0\u00d7); Net Debt/EBITDA=-1.0x \u2014 net cash position (0.95\u00d7)"
      }
    ],
    "\u20b91000\u2013\u20b91500": [
      {
        "Price_Band": "\u20b91000\u2013\u20b91500",
        "Stock": "PREMIERENE.NS",
        "Company_Name": "PREMIER ENERGIES LIMITED",
        "Buy_Price": 1100.0,
        "Exit_Target": 1223.82,
        "Gross_ROI_%": 9.08,
        "After_Tax_ROI_%": 8.87,
        "Tax_Type": "LTCG",
        "Min_Hold_Until": "01 Jul 2027",
        "Best_Sell_Date": "03 Jan 2028",
        "Forecast_Expires": "21 Jan 2028",
        "Avg_Daily_Turnover_Cr": 120.49,
        "Sector": "Technology",
        "Liquidity": "High",
        "Data_Days": 464,
        "Predicted_Best_Buy_Date": "07 Aug 2026",
        "Predicted_Best_Buy_Price": 1102.74,
        "Fundamental_Risk": "Low",
        "Risk_Score": 3,
        "Risk_Reasons": "PE=32.7 within limit=50 (1.0\u00d7); D/E=0.86 within limit=2.0 (1.0\u00d7); Revenue growth=37.6% \u2192 0.85\u00d7; All 3 fields present (1.0\u00d7); ROE=42.3% \u2014 strong (0.90\u00d7); EV/EBITDA=21.5x within limit=30x (1.0\u00d7); Earnings quality=0.84 \u2014 adequate (1.0\u00d7); Net Debt/EBITDA=0.5x within limit=3.5x (1.0\u00d7)"
      }
    ],
    "\u20b91500\u2013\u20b92000": [
      {
        "Price_Band": "\u20b91500\u2013\u20b92000",
        "Stock": "IKS.NS",
        "Company_Name": "INVENTURUS KNOWLEDGE SO L",
        "Buy_Price": 1881.5,
        "Exit_Target": 2084.64,
        "Gross_ROI_%": 8.62,
        "After_Tax_ROI_%": 8.42,
        "Tax_Type": "LTCG",
        "Min_Hold_Until": "01 Jul 2027",
        "Best_Sell_Date": "25 Feb 2028",
        "Forecast_Expires": "19 Jun 2028",
        "Avg_Daily_Turnover_Cr": 56.14,
        "Sector": "Healthcare",
        "Liquidity": "High",
        "Data_Days": 389,
        "Predicted_Best_Buy_Date": "14 Aug 2026",
        "Predicted_Best_Buy_Price": 1862.76,
        "Fundamental_Risk": "Low",
        "Risk_Score": 8,
        "Risk_Reasons": "PE=44.6 within limit=76 (1.0\u00d7); D/E=0.27 within limit=2.75 (1.0\u00d7); Revenue growth=18.5% \u2192 0.85\u00d7; All 3 fields present (1.0\u00d7); ROE=31.4% \u2014 strong (0.90\u00d7); EV/EBITDA=29.3x vs limit=25x (1.15\u00d7); Earnings quality=0.93 \u2014 adequate (1.0\u00d7); Net Debt/EBITDA=0.1x within limit=3.5x (1.0\u00d7)"
      }
    ],
    "\u20b92000\u2013\u20b92500": [
      {
        "Price_Band": "\u20b92000\u2013\u20b92500",
        "Stock": "ANANDRATHI.NS",
        "Company_Name": "Anand Rathi Wealth Limited",
        "Buy_Price": 2082.0,
        "Exit_Target": 2288.22,
        "Gross_ROI_%": 7.75,
        "After_Tax_ROI_%": 7.54,
        "Tax_Type": "LTCG",
        "Min_Hold_Until": "01 Jul 2027",
        "Best_Sell_Date": "08 Nov 2027",
        "Forecast_Expires": "08 Nov 2027",
        "Avg_Daily_Turnover_Cr": 136.01,
        "Sector": "Financial Services",
        "Liquidity": "High",
        "Data_Days": 742,
        "Predicted_Best_Buy_Date": "15 Jul 2026",
        "Predicted_Best_Buy_Price": 2082.77,
        "Fundamental_Risk": "Medium",
        "Risk_Score": 39,
        "Risk_Reasons": "PE=75.2 vs limit=45 \u2192 1.67\u00d7 (2.65\u00d7); D/E exempt \u2014 financial sector (1.0\u00d7); Revenue growth=52.1% \u2192 0.85\u00d7; All 3 fields present (1.0\u00d7); ROE unavailable \u2014 no multiplier; EV/EBITDA exempt \u2014 financial sector (1.0\u00d7); Earnings quality unavailable \u2014 no multiplier; Net Debt/EBITDA=-0.6x \u2014 net cash position (0.95\u00d7)"
      }
    ],
    "\u20b97000\u2013\u20b915000": [
      {
        "Price_Band": "\u20b97000\u2013\u20b915000",
        "Stock": "OFSS.NS",
        "Company_Name": "Oracle Financial Services Software Limited",
        "Buy_Price": 11651.0,
        "Exit_Target": 12921.22,
        "Gross_ROI_%": 8.73,
        "After_Tax_ROI_%": 8.52,
        "Tax_Type": "LTCG",
        "Min_Hold_Until": "01 Jul 2027",
        "Best_Sell_Date": "12 Jan 2028",
        "Forecast_Expires": "12 Jan 2028",
        "Avg_Daily_Turnover_Cr": 346.83,
        "Sector": "Technology",
        "Liquidity": "High",
        "Data_Days": 742,
        "Predicted_Best_Buy_Date": "17 Jul 2026",
        "Predicted_Best_Buy_Price": 11653.99,
        "Fundamental_Risk": "Low",
        "Risk_Score": 1,
        "Risk_Reasons": "PE=38.3 within limit=65 (1.0\u00d7); D/E=0.00 within limit=2.0 (1.0\u00d7); Revenue growth=20.3% \u2192 0.85\u00d7; All 3 fields present (1.0\u00d7); ROE=32.6% \u2014 strong (0.90\u00d7); EV/EBITDA=28.0x within limit=30x (1.0\u00d7); Earnings quality=1.00 \u2014 adequate (1.0\u00d7); Net Debt/EBITDA=-1.6x \u2014 net cash position (0.95\u00d7)"
      }
    ]
  },
  "portfolios": [
    {
      "name": "Best Overall (Composite Score)",
      "description": "Highest composite score: ROI \u00d7 liquidity \u00d7 sell month \u00d7 risk penalty \u2014 most well-rounded",
      "summary": {
        "Total_Invested": 49594.95,
        "Total_Net_Profit": 6879.66,
        "Portfolio_ROI_%": 13.87,
        "Earliest_Sell": "01 Oct 2027",
        "Latest_Sell": "26 Apr 2028",
        "Num_Stocks": 6,
        "Risk_Breakdown": {
          "Low": 5,
          "Medium": 1
        }
      },
      "portfolio": [
        {
          "Stock": "GPIL.NS",
          "Company_Name": "Godawari Power & Ispat Limited",
          "Band": "\u20b90\u2013\u20b9500",
          "Buy_Price": 251.25,
          "Shares": 38,
          "Invested": 9601.41,
          "Exit_Target": 307.56,
          "Exit_Value": 11687.28,
          "Gross_Profit": 2139.78,
          "Net_Profit": 2000.36,
          "Net_ROI_%": 20.83,
          "Best_Sell_Date": "03 Jan 2028",
          "Forecast_Expires": "03 Jan 2028",
          "Predicted_Best_Buy_Date": "17 Jul 2026",
          "Predicted_Best_Buy_Price": 248.67,
          "Turnover_Cr": 32.54,
          "Fundamental_Risk": "Low",
          "Risk_Score": 7
        },
        {
          "Stock": "NATCOPHARM.NS",
          "Company_Name": "NATCO Pharma Limited",
          "Band": "\u20b9500\u2013\u20b91000",
          "Buy_Price": 970.2,
          "Shares": 10,
          "Invested": 9755.91,
          "Exit_Target": 1181.36,
          "Exit_Value": 11813.6,
          "Gross_Profit": 2111.6,
          "Net_Profit": 1971.2,
          "Net_ROI_%": 20.21,
          "Best_Sell_Date": "01 Oct 2027",
          "Forecast_Expires": "01 Oct 2027",
          "Predicted_Best_Buy_Date": "15 Jul 2026",
          "Predicted_Best_Buy_Price": 972.53,
          "Turnover_Cr": 64.53,
          "Fundamental_Risk": "Medium",
          "Risk_Score": 38
        },
        {
          "Stock": "PREMIERENE.NS",
          "Company_Name": "PREMIER ENERGIES LIMITED",
          "Band": "\u20b91000\u2013\u20b91500",
          "Buy_Price": 1100.0,
          "Shares": 8,
          "Invested": 8848.4,
          "Exit_Target": 1223.82,
          "Exit_Value": 9790.56,
          "Gross_Profit": 990.56,
          "Net_Profit": 869.72,
          "Net_ROI_%": 9.83,
          "Best_Sell_Date": "03 Jan 2028",
          "Forecast_Expires": "21 Jan 2028",
          "Predicted_Best_Buy_Date": "07 Aug 2026",
          "Predicted_Best_Buy_Price": 1102.74,
          "Turnover_Cr": 120.49,
          "Fundamental_Risk": "Low",
          "Risk_Score": 3
        },
        {
          "Stock": "HINDCOPPER.NS",
          "Company_Name": "Hindustan Copper Limited",
          "Band": "\u20b90\u2013\u20b9500",
          "Buy_Price": 490.0,
          "Shares": 18,
          "Invested": 8868.51,
          "Exit_Target": 543.6,
          "Exit_Value": 9784.8,
          "Gross_Profit": 964.8,
          "Net_Profit": 843.87,
          "Net_ROI_%": 9.52,
          "Best_Sell_Date": "15 Jul 2027",
          "Forecast_Expires": "06 Sep 2027",
          "Predicted_Best_Buy_Date": "25 Aug 2026",
          "Predicted_Best_Buy_Price": 487.12,
          "Turnover_Cr": 169.02,
          "Fundamental_Risk": "Low",
          "Risk_Score": 17
        },
        {
          "Stock": "IKS.NS",
          "Company_Name": "INVENTURUS KNOWLEDGE SO L",
          "Band": "\u20b91500\u2013\u20b92000",
          "Buy_Price": 1881.5,
          "Shares": 4,
          "Invested": 7567.39,
          "Exit_Target": 2084.64,
          "Exit_Value": 8338.56,
          "Gross_Profit": 812.56,
          "Net_Profit": 709.44,
          "Net_ROI_%": 9.37,
          "Best_Sell_Date": "25 Feb 2028",
          "Forecast_Expires": "19 Jun 2028",
          "Predicted_Best_Buy_Date": "14 Aug 2026",
          "Predicted_Best_Buy_Price": 1862.76,
          "Turnover_Cr": 56.14,
          "Fundamental_Risk": "Low",
          "Risk_Score": 8
        },
        {
          "Stock": "MAHABANK.NS",
          "Company_Name": "Bank of Maharashtra",
          "Band": "\u20b90\u2013\u20b9500",
          "Buy_Price": 79.45,
          "Shares": 62,
          "Invested": 4953.33,
          "Exit_Target": 88.37,
          "Exit_Value": 5478.94,
          "Gross_Profit": 553.04,
          "Net_Profit": 485.07,
          "Net_ROI_%": 9.79,
          "Best_Sell_Date": "26 Apr 2028",
          "Forecast_Expires": "19 Jun 2028",
          "Predicted_Best_Buy_Date": "15 Jul 2026",
          "Predicted_Best_Buy_Price": 79.46,
          "Turnover_Cr": 172.11,
          "Fundamental_Risk": "Low",
          "Risk_Score": 13
        }
      ]
    },
    {
      "name": "Max After-Tax Return",
      "description": "Top stocks by after-tax ROI \u2014 highest yield, check Risk column for each stock",
      "summary": {
        "Total_Invested": 49049.37,
        "Total_Net_Profit": 7125.02,
        "Portfolio_ROI_%": 14.53,
        "Earliest_Sell": "01 Oct 2027",
        "Latest_Sell": "26 Apr 2028",
        "Num_Stocks": 7,
        "Risk_Breakdown": {
          "Low": 4,
          "Medium": 2,
          "High": 1
        }
      },
      "portfolio": [
        {
          "Stock": "GPIL.NS",
          "Company_Name": "Godawari Power & Ispat Limited",
          "Band": "\u20b90\u2013\u20b9500",
          "Buy_Price": 251.25,
          "Shares": 41,
          "Invested": 10359.32,
          "Exit_Target": 307.56,
          "Exit_Value": 12609.96,
          "Gross_Profit": 2308.71,
          "Net_Profit": 2158.38,
          "Net_ROI_%": 20.84,
          "Best_Sell_Date": "03 Jan 2028",
          "Forecast_Expires": "03 Jan 2028",
          "Predicted_Best_Buy_Date": "17 Jul 2026",
          "Predicted_Best_Buy_Price": 248.67,
          "Turnover_Cr": 32.54,
          "Fundamental_Risk": "Low",
          "Risk_Score": 7
        },
        {
          "Stock": "NATCOPHARM.NS",
          "Company_Name": "NATCO Pharma Limited",
          "Band": "\u20b9500\u2013\u20b91000",
          "Buy_Price": 970.2,
          "Shares": 10,
          "Invested": 9760.07,
          "Exit_Target": 1181.36,
          "Exit_Value": 11813.6,
          "Gross_Profit": 2111.6,
          "Net_Profit": 1967.04,
          "Net_ROI_%": 20.15,
          "Best_Sell_Date": "01 Oct 2027",
          "Forecast_Expires": "01 Oct 2027",
          "Predicted_Best_Buy_Date": "15 Jul 2026",
          "Predicted_Best_Buy_Price": 972.53,
          "Turnover_Cr": 64.53,
          "Fundamental_Risk": "Medium",
          "Risk_Score": 38
        },
        {
          "Stock": "TMCV.NS",
          "Company_Name": "TATA MOTORS LIMITED",
          "Band": "\u20b90\u2013\u20b9500",
          "Buy_Price": 416.75,
          "Shares": 13,
          "Invested": 5449.79,
          "Exit_Target": 476.54,
          "Exit_Value": 6195.02,
          "Gross_Profit": 777.27,
          "Net_Profit": 699.54,
          "Net_ROI_%": 12.84,
          "Best_Sell_Date": "20 Oct 2027",
          "Forecast_Expires": "20 Oct 2027",
          "Predicted_Best_Buy_Date": "23 Jul 2026",
          "Predicted_Best_Buy_Price": 415.1,
          "Turnover_Cr": 338.53,
          "Fundamental_Risk": "High",
          "Risk_Score": 84
        },
        {
          "Stock": "PREMIERENE.NS",
          "Company_Name": "PREMIER ENERGIES LIMITED",
          "Band": "\u20b91000\u2013\u20b91500",
          "Buy_Price": 1100.0,
          "Shares": 8,
          "Invested": 8848.4,
          "Exit_Target": 1223.82,
          "Exit_Value": 9790.56,
          "Gross_Profit": 990.56,
          "Net_Profit": 869.72,
          "Net_ROI_%": 9.83,
          "Best_Sell_Date": "03 Jan 2028",
          "Forecast_Expires": "21 Jan 2028",
          "Predicted_Best_Buy_Date": "07 Aug 2026",
          "Predicted_Best_Buy_Price": 1102.74,
          "Turnover_Cr": 120.49,
          "Fundamental_Risk": "Low",
          "Risk_Score": 3
        },
        {
          "Stock": "MAHABANK.NS",
          "Company_Name": "Bank of Maharashtra",
          "Band": "\u20b90\u2013\u20b9500",
          "Buy_Price": 79.45,
          "Shares": 77,
          "Invested": 6151.6,
          "Exit_Target": 88.37,
          "Exit_Value": 6804.49,
          "Gross_Profit": 686.84,
          "Net_Profit": 602.55,
          "Net_ROI_%": 9.79,
          "Best_Sell_Date": "26 Apr 2028",
          "Forecast_Expires": "19 Jun 2028",
          "Predicted_Best_Buy_Date": "15 Jul 2026",
          "Predicted_Best_Buy_Price": 79.46,
          "Turnover_Cr": 172.11,
          "Fundamental_Risk": "Low",
          "Risk_Score": 13
        },
        {
          "Stock": "JINDALSAW.NS",
          "Company_Name": "Jindal Saw Limited",
          "Band": "\u20b90\u2013\u20b9500",
          "Buy_Price": 267.3,
          "Shares": 15,
          "Invested": 4032.22,
          "Exit_Target": 297.33,
          "Exit_Value": 4459.95,
          "Gross_Profit": 450.45,
          "Net_Profit": 394.73,
          "Net_ROI_%": 9.79,
          "Best_Sell_Date": "12 Jun 2028",
          "Forecast_Expires": "19 Jun 2028",
          "Predicted_Best_Buy_Date": "21 Jul 2026",
          "Predicted_Best_Buy_Price": 267.83,
          "Turnover_Cr": 46.58,
          "Fundamental_Risk": "Medium",
          "Risk_Score": 37
        },
        {
          "Stock": "THELEELA.NS",
          "Company_Name": "Leela Palaces Hotels & Resorts Limited",
          "Band": "\u20b90\u2013\u20b9500",
          "Buy_Price": 491.45,
          "Shares": 9,
          "Invested": 4447.97,
          "Exit_Target": 546.38,
          "Exit_Value": 4917.42,
          "Gross_Profit": 494.37,
          "Net_Profit": 433.06,
          "Net_ROI_%": 9.74,
          "Best_Sell_Date": "12 Jun 2028",
          "Forecast_Expires": "19 Jun 2028",
          "Predicted_Best_Buy_Date": "15 Jul 2026",
          "Predicted_Best_Buy_Price": 492.11,
          "Turnover_Cr": 27.64,
          "Fundamental_Risk": "Low",
          "Risk_Score": 29
        }
      ]
    },
    {
      "name": "Balanced Cap Mix",
      "description": "4 each from small / mid / large cap \u2014 diversified across market cap segments",
      "summary": {
        "Total_Invested": 38527.17,
        "Total_Net_Profit": 4736.64,
        "Portfolio_ROI_%": 12.29,
        "Earliest_Sell": "01 Oct 2027",
        "Latest_Sell": "25 Feb 2028",
        "Num_Stocks": 4,
        "Risk_Breakdown": {
          "Medium": 2,
          "Low": 2
        }
      },
      "portfolio": [
        {
          "Stock": "NATCOPHARM.NS",
          "Company_Name": "NATCO Pharma Limited",
          "Band": "\u20b9500\u2013\u20b91000",
          "Buy_Price": 970.2,
          "Shares": 11,
          "Invested": 10732.33,
          "Exit_Target": 1181.36,
          "Exit_Value": 12994.96,
          "Gross_Profit": 2322.76,
          "Net_Profit": 2167.49,
          "Net_ROI_%": 20.2,
          "Best_Sell_Date": "01 Oct 2027",
          "Forecast_Expires": "01 Oct 2027",
          "Predicted_Best_Buy_Date": "15 Jul 2026",
          "Predicted_Best_Buy_Price": 972.53,
          "Turnover_Cr": 64.53,
          "Fundamental_Risk": "Medium",
          "Risk_Score": 38
        },
        {
          "Stock": "PREMIERENE.NS",
          "Company_Name": "PREMIER ENERGIES LIMITED",
          "Band": "\u20b91000\u2013\u20b91500",
          "Buy_Price": 1100.0,
          "Shares": 9,
          "Invested": 9960.13,
          "Exit_Target": 1223.82,
          "Exit_Value": 11014.38,
          "Gross_Profit": 1114.38,
          "Net_Profit": 972.76,
          "Net_ROI_%": 9.77,
          "Best_Sell_Date": "03 Jan 2028",
          "Forecast_Expires": "21 Jan 2028",
          "Predicted_Best_Buy_Date": "07 Aug 2026",
          "Predicted_Best_Buy_Price": 1102.74,
          "Turnover_Cr": 120.49,
          "Fundamental_Risk": "Low",
          "Risk_Score": 3
        },
        {
          "Stock": "IKS.NS",
          "Company_Name": "INVENTURUS KNOWLEDGE SO L",
          "Band": "\u20b91500\u2013\u20b92000",
          "Buy_Price": 1881.5,
          "Shares": 5,
          "Invested": 9460.91,
          "Exit_Target": 2084.64,
          "Exit_Value": 10423.2,
          "Gross_Profit": 1015.7,
          "Net_Profit": 885.14,
          "Net_ROI_%": 9.36,
          "Best_Sell_Date": "25 Feb 2028",
          "Forecast_Expires": "19 Jun 2028",
          "Predicted_Best_Buy_Date": "14 Aug 2026",
          "Predicted_Best_Buy_Price": 1862.76,
          "Turnover_Cr": 56.14,
          "Fundamental_Risk": "Low",
          "Risk_Score": 8
        },
        {
          "Stock": "ANANDRATHI.NS",
          "Company_Name": "Anand Rathi Wealth Limited",
          "Band": "\u20b92000\u2013\u20b92500",
          "Buy_Price": 2082.0,
          "Shares": 4,
          "Invested": 8373.8,
          "Exit_Target": 2288.22,
          "Exit_Value": 9152.88,
          "Gross_Profit": 824.88,
          "Net_Profit": 711.25,
          "Net_ROI_%": 8.49,
          "Best_Sell_Date": "08 Nov 2027",
          "Forecast_Expires": "08 Nov 2027",
          "Predicted_Best_Buy_Date": "15 Jul 2026",
          "Predicted_Best_Buy_Price": 2082.77,
          "Turnover_Cr": 136.01,
          "Fundamental_Risk": "Medium",
          "Risk_Score": 39
        }
      ]
    },
    {
      "name": "High Liquidity",
      "description": "Top stocks by daily turnover \u2014 easiest to exit without moving the price",
      "summary": {
        "Total_Invested": 49012.17,
        "Total_Net_Profit": 4921.77,
        "Portfolio_ROI_%": 10.04,
        "Earliest_Sell": "03 Jan 2028",
        "Latest_Sell": "26 Apr 2028",
        "Num_Stocks": 6,
        "Risk_Breakdown": {
          "Low": 3,
          "High": 2,
          "Medium": 1
        }
      },
      "portfolio": [
        {
          "Stock": "IFCI.NS",
          "Company_Name": "IFCI Limited",
          "Band": "\u20b90\u2013\u20b9500",
          "Buy_Price": 74.56,
          "Shares": 69,
          "Invested": 5173.12,
          "Exit_Target": 82.65,
          "Exit_Value": 5702.85,
          "Gross_Profit": 558.21,
          "Net_Profit": 487.52,
          "Net_ROI_%": 9.42,
          "Best_Sell_Date": "09 Feb 2028",
          "Forecast_Expires": "20 Mar 2028",
          "Predicted_Best_Buy_Date": "15 Jul 2026",
          "Predicted_Best_Buy_Price": 74.61,
          "Turnover_Cr": 554.38,
          "Fundamental_Risk": "High",
          "Risk_Score": 76
        },
        {
          "Stock": "TMCV.NS",
          "Company_Name": "TATA MOTORS LIMITED",
          "Band": "\u20b90\u2013\u20b9500",
          "Buy_Price": 416.75,
          "Shares": 21,
          "Invested": 8799.88,
          "Exit_Target": 476.54,
          "Exit_Value": 10007.34,
          "Gross_Profit": 1255.59,
          "Net_Profit": 1133.66,
          "Net_ROI_%": 12.88,
          "Best_Sell_Date": "20 Oct 2027",
          "Forecast_Expires": "20 Oct 2027",
          "Predicted_Best_Buy_Date": "23 Jul 2026",
          "Predicted_Best_Buy_Price": 415.1,
          "Turnover_Cr": 338.53,
          "Fundamental_Risk": "High",
          "Risk_Score": 84
        },
        {
          "Stock": "MAHABANK.NS",
          "Company_Name": "Bank of Maharashtra",
          "Band": "\u20b90\u2013\u20b9500",
          "Buy_Price": 79.45,
          "Shares": 112,
          "Invested": 8947.34,
          "Exit_Target": 88.37,
          "Exit_Value": 9897.44,
          "Gross_Profit": 999.04,
          "Net_Profit": 876.87,
          "Net_ROI_%": 9.8,
          "Best_Sell_Date": "26 Apr 2028",
          "Forecast_Expires": "19 Jun 2028",
          "Predicted_Best_Buy_Date": "15 Jul 2026",
          "Predicted_Best_Buy_Price": 79.46,
          "Turnover_Cr": 172.11,
          "Fundamental_Risk": "Low",
          "Risk_Score": 13
        },
        {
          "Stock": "HINDCOPPER.NS",
          "Company_Name": "Hindustan Copper Limited",
          "Band": "\u20b90\u2013\u20b9500",
          "Buy_Price": 490.0,
          "Shares": 18,
          "Invested": 8868.51,
          "Exit_Target": 543.6,
          "Exit_Value": 9784.8,
          "Gross_Profit": 964.8,
          "Net_Profit": 843.87,
          "Net_ROI_%": 9.52,
          "Best_Sell_Date": "15 Jul 2027",
          "Forecast_Expires": "06 Sep 2027",
          "Predicted_Best_Buy_Date": "25 Aug 2026",
          "Predicted_Best_Buy_Price": 487.12,
          "Turnover_Cr": 169.02,
          "Fundamental_Risk": "Low",
          "Risk_Score": 17
        },
        {
          "Stock": "ANANDRATHI.NS",
          "Company_Name": "Anand Rathi Wealth Limited",
          "Band": "\u20b92000\u2013\u20b92500",
          "Buy_Price": 2082.0,
          "Shares": 4,
          "Invested": 8373.8,
          "Exit_Target": 2288.22,
          "Exit_Value": 9152.88,
          "Gross_Profit": 824.88,
          "Net_Profit": 711.25,
          "Net_ROI_%": 8.49,
          "Best_Sell_Date": "08 Nov 2027",
          "Forecast_Expires": "08 Nov 2027",
          "Predicted_Best_Buy_Date": "15 Jul 2026",
          "Predicted_Best_Buy_Price": 2082.77,
          "Turnover_Cr": 136.01,
          "Fundamental_Risk": "Medium",
          "Risk_Score": 39
        },
        {
          "Stock": "PREMIERENE.NS",
          "Company_Name": "PREMIER ENERGIES LIMITED",
          "Band": "\u20b91000\u2013\u20b91500",
          "Buy_Price": 1100.0,
          "Shares": 8,
          "Invested": 8849.52,
          "Exit_Target": 1223.82,
          "Exit_Value": 9790.56,
          "Gross_Profit": 990.56,
          "Net_Profit": 868.6,
          "Net_ROI_%": 9.82,
          "Best_Sell_Date": "03 Jan 2028",
          "Forecast_Expires": "21 Jan 2028",
          "Predicted_Best_Buy_Date": "07 Aug 2026",
          "Predicted_Best_Buy_Price": 1102.74,
          "Turnover_Cr": 120.49,
          "Fundamental_Risk": "Low",
          "Risk_Score": 3
        }
      ]
    },
    {
      "name": "Mid-2027 Exit (Jul\u2013Oct)",
      "description": "Peaks Jul\u2013Oct 2027 \u2014 exit before year-end, redeploy for next cycle early",
      "summary": {
        "Total_Invested": 49191.66,
        "Total_Net_Profit": 6998.47,
        "Portfolio_ROI_%": 14.23,
        "Earliest_Sell": "01 Oct 2027",
        "Latest_Sell": "20 Oct 2027",
        "Num_Stocks": 3,
        "Risk_Breakdown": {
          "Medium": 1,
          "High": 1,
          "Low": 1
        }
      },
      "portfolio": [
        {
          "Stock": "NATCOPHARM.NS",
          "Company_Name": "NATCO Pharma Limited",
          "Band": "\u20b9500\u2013\u20b91000",
          "Buy_Price": 970.2,
          "Shares": 17,
          "Invested": 16585.07,
          "Exit_Target": 1181.36,
          "Exit_Value": 20083.12,
          "Gross_Profit": 3589.72,
          "Net_Profit": 3351.02,
          "Net_ROI_%": 20.21,
          "Best_Sell_Date": "01 Oct 2027",
          "Forecast_Expires": "01 Oct 2027",
          "Predicted_Best_Buy_Date": "15 Jul 2026",
          "Predicted_Best_Buy_Price": 972.53,
          "Turnover_Cr": 64.53,
          "Fundamental_Risk": "Medium",
          "Risk_Score": 38
        },
        {
          "Stock": "TMCV.NS",
          "Company_Name": "TATA MOTORS LIMITED",
          "Band": "\u20b90\u2013\u20b9500",
          "Buy_Price": 416.75,
          "Shares": 39,
          "Invested": 16344.92,
          "Exit_Target": 476.54,
          "Exit_Value": 18585.06,
          "Gross_Profit": 2331.81,
          "Net_Profit": 2103.09,
          "Net_ROI_%": 12.87,
          "Best_Sell_Date": "20 Oct 2027",
          "Forecast_Expires": "20 Oct 2027",
          "Predicted_Best_Buy_Date": "23 Jul 2026",
          "Predicted_Best_Buy_Price": 415.1,
          "Turnover_Cr": 338.53,
          "Fundamental_Risk": "High",
          "Risk_Score": 84
        },
        {
          "Stock": "HINDCOPPER.NS",
          "Company_Name": "Hindustan Copper Limited",
          "Band": "\u20b90\u2013\u20b9500",
          "Buy_Price": 490.0,
          "Shares": 33,
          "Invested": 16261.67,
          "Exit_Target": 543.6,
          "Exit_Value": 17938.8,
          "Gross_Profit": 1768.8,
          "Net_Profit": 1544.36,
          "Net_ROI_%": 9.5,
          "Best_Sell_Date": "15 Jul 2027",
          "Forecast_Expires": "06 Sep 2027",
          "Predicted_Best_Buy_Date": "25 Aug 2026",
          "Predicted_Best_Buy_Price": 487.12,
          "Turnover_Cr": 169.02,
          "Fundamental_Risk": "Low",
          "Risk_Score": 17
        }
      ]
    },
    {
      "name": "Patient Hold (2028 exit)",
      "description": "Peaks in 2028 \u2014 maximum LTCG window, full mean reversion cycle",
      "summary": {
        "Total_Invested": 49681.08,
        "Total_Net_Profit": 5974.26,
        "Portfolio_ROI_%": 12.03,
        "Earliest_Sell": "03 Jan 2028",
        "Latest_Sell": "26 Apr 2028",
        "Num_Stocks": 6,
        "Risk_Breakdown": {
          "Low": 5,
          "Medium": 1
        }
      },
      "portfolio": [
        {
          "Stock": "GPIL.NS",
          "Company_Name": "Godawari Power & Ispat Limited",
          "Band": "\u20b90\u2013\u20b9500",
          "Buy_Price": 251.25,
          "Shares": 40,
          "Invested": 10106.18,
          "Exit_Target": 307.56,
          "Exit_Value": 12302.4,
          "Gross_Profit": 2252.4,
          "Net_Profit": 2106.2,
          "Net_ROI_%": 20.84,
          "Best_Sell_Date": "03 Jan 2028",
          "Forecast_Expires": "03 Jan 2028",
          "Predicted_Best_Buy_Date": "17 Jul 2026",
          "Predicted_Best_Buy_Price": 248.67,
          "Turnover_Cr": 32.54,
          "Fundamental_Risk": "Low",
          "Risk_Score": 7
        },
        {
          "Stock": "PREMIERENE.NS",
          "Company_Name": "PREMIER ENERGIES LIMITED",
          "Band": "\u20b91000\u2013\u20b91500",
          "Buy_Price": 1100.0,
          "Shares": 8,
          "Invested": 8848.4,
          "Exit_Target": 1223.82,
          "Exit_Value": 9790.56,
          "Gross_Profit": 990.56,
          "Net_Profit": 869.72,
          "Net_ROI_%": 9.83,
          "Best_Sell_Date": "03 Jan 2028",
          "Forecast_Expires": "21 Jan 2028",
          "Predicted_Best_Buy_Date": "07 Aug 2026",
          "Predicted_Best_Buy_Price": 1102.74,
          "Turnover_Cr": 120.49,
          "Fundamental_Risk": "Low",
          "Risk_Score": 3
        },
        {
          "Stock": "MAHABANK.NS",
          "Company_Name": "Bank of Maharashtra",
          "Band": "\u20b90\u2013\u20b9500",
          "Buy_Price": 79.45,
          "Shares": 112,
          "Invested": 8947.34,
          "Exit_Target": 88.37,
          "Exit_Value": 9897.44,
          "Gross_Profit": 999.04,
          "Net_Profit": 876.87,
          "Net_ROI_%": 9.8,
          "Best_Sell_Date": "26 Apr 2028",
          "Forecast_Expires": "19 Jun 2028",
          "Predicted_Best_Buy_Date": "15 Jul 2026",
          "Predicted_Best_Buy_Price": 79.46,
          "Turnover_Cr": 172.11,
          "Fundamental_Risk": "Low",
          "Risk_Score": 13
        },
        {
          "Stock": "JINDALSAW.NS",
          "Company_Name": "Jindal Saw Limited",
          "Band": "\u20b90\u2013\u20b9500",
          "Buy_Price": 267.3,
          "Shares": 15,
          "Invested": 4033.04,
          "Exit_Target": 297.33,
          "Exit_Value": 4459.95,
          "Gross_Profit": 450.45,
          "Net_Profit": 393.91,
          "Net_ROI_%": 9.77,
          "Best_Sell_Date": "12 Jun 2028",
          "Forecast_Expires": "19 Jun 2028",
          "Predicted_Best_Buy_Date": "21 Jul 2026",
          "Predicted_Best_Buy_Price": 267.83,
          "Turnover_Cr": 46.58,
          "Fundamental_Risk": "Medium",
          "Risk_Score": 37
        },
        {
          "Stock": "THELEELA.NS",
          "Company_Name": "Leela Palaces Hotels & Resorts Limited",
          "Band": "\u20b90\u2013\u20b9500",
          "Buy_Price": 491.45,
          "Shares": 18,
          "Invested": 8894.75,
          "Exit_Target": 546.38,
          "Exit_Value": 9834.84,
          "Gross_Profit": 988.74,
          "Net_Profit": 867.31,
          "Net_ROI_%": 9.75,
          "Best_Sell_Date": "12 Jun 2028",
          "Forecast_Expires": "19 Jun 2028",
          "Predicted_Best_Buy_Date": "15 Jul 2026",
          "Predicted_Best_Buy_Price": 492.11,
          "Turnover_Cr": 27.64,
          "Fundamental_Risk": "Low",
          "Risk_Score": 29
        },
        {
          "Stock": "NLCINDIA.NS",
          "Company_Name": "NLC India Limited",
          "Band": "\u20b90\u2013\u20b9500",
          "Buy_Price": 303.55,
          "Shares": 29,
          "Invested": 8851.37,
          "Exit_Target": 337.38,
          "Exit_Value": 9784.02,
          "Gross_Profit": 981.07,
          "Net_Profit": 860.25,
          "Net_ROI_%": 9.72,
          "Best_Sell_Date": "16 May 2028",
          "Forecast_Expires": "19 Jun 2028",
          "Predicted_Best_Buy_Date": "15 Jul 2026",
          "Predicted_Best_Buy_Price": 303.6,
          "Turnover_Cr": 109.29,
          "Fundamental_Risk": "Low",
          "Risk_Score": 13
        }
      ]
    },
    {
      "name": "Low Risk Preference",
      "description": "Same pool, sorted to show cleanest fundamentals first \u2014 Low risk stocks lead",
      "summary": {
        "Total_Invested": 49579.35,
        "Total_Net_Profit": 5887.18,
        "Portfolio_ROI_%": 11.87,
        "Earliest_Sell": "03 Jan 2028",
        "Latest_Sell": "26 Apr 2028",
        "Num_Stocks": 6,
        "Risk_Breakdown": {
          "Low": 6
        }
      },
      "portfolio": [
        {
          "Stock": "GPIL.NS",
          "Company_Name": "Godawari Power & Ispat Limited",
          "Band": "\u20b90\u2013\u20b9500",
          "Buy_Price": 251.25,
          "Shares": 39,
          "Invested": 9853.32,
          "Exit_Target": 307.56,
          "Exit_Value": 11994.84,
          "Gross_Profit": 2196.09,
          "Net_Profit": 2053.76,
          "Net_ROI_%": 20.84,
          "Best_Sell_Date": "03 Jan 2028",
          "Forecast_Expires": "03 Jan 2028",
          "Predicted_Best_Buy_Date": "17 Jul 2026",
          "Predicted_Best_Buy_Price": 248.67,
          "Turnover_Cr": 32.54,
          "Fundamental_Risk": "Low",
          "Risk_Score": 7
        },
        {
          "Stock": "PREMIERENE.NS",
          "Company_Name": "PREMIER ENERGIES LIMITED",
          "Band": "\u20b91000\u2013\u20b91500",
          "Buy_Price": 1100.0,
          "Shares": 8,
          "Invested": 8848.4,
          "Exit_Target": 1223.82,
          "Exit_Value": 9790.56,
          "Gross_Profit": 990.56,
          "Net_Profit": 869.72,
          "Net_ROI_%": 9.83,
          "Best_Sell_Date": "03 Jan 2028",
          "Forecast_Expires": "21 Jan 2028",
          "Predicted_Best_Buy_Date": "07 Aug 2026",
          "Predicted_Best_Buy_Price": 1102.74,
          "Turnover_Cr": 120.49,
          "Fundamental_Risk": "Low",
          "Risk_Score": 3
        },
        {
          "Stock": "HINDCOPPER.NS",
          "Company_Name": "Hindustan Copper Limited",
          "Band": "\u20b90\u2013\u20b9500",
          "Buy_Price": 490.0,
          "Shares": 18,
          "Invested": 8868.51,
          "Exit_Target": 543.6,
          "Exit_Value": 9784.8,
          "Gross_Profit": 964.8,
          "Net_Profit": 843.87,
          "Net_ROI_%": 9.52,
          "Best_Sell_Date": "15 Jul 2027",
          "Forecast_Expires": "06 Sep 2027",
          "Predicted_Best_Buy_Date": "25 Aug 2026",
          "Predicted_Best_Buy_Price": 487.12,
          "Turnover_Cr": 169.02,
          "Fundamental_Risk": "Low",
          "Risk_Score": 17
        },
        {
          "Stock": "IKS.NS",
          "Company_Name": "INVENTURUS KNOWLEDGE SO L",
          "Band": "\u20b91500\u2013\u20b92000",
          "Buy_Price": 1881.5,
          "Shares": 4,
          "Invested": 7567.39,
          "Exit_Target": 2084.64,
          "Exit_Value": 8338.56,
          "Gross_Profit": 812.56,
          "Net_Profit": 709.44,
          "Net_ROI_%": 9.37,
          "Best_Sell_Date": "25 Feb 2028",
          "Forecast_Expires": "19 Jun 2028",
          "Predicted_Best_Buy_Date": "14 Aug 2026",
          "Predicted_Best_Buy_Price": 1862.76,
          "Turnover_Cr": 56.14,
          "Fundamental_Risk": "Low",
          "Risk_Score": 8
        },
        {
          "Stock": "MAHABANK.NS",
          "Company_Name": "Bank of Maharashtra",
          "Band": "\u20b90\u2013\u20b9500",
          "Buy_Price": 79.45,
          "Shares": 112,
          "Invested": 8947.34,
          "Exit_Target": 88.37,
          "Exit_Value": 9897.44,
          "Gross_Profit": 999.04,
          "Net_Profit": 876.87,
          "Net_ROI_%": 9.8,
          "Best_Sell_Date": "26 Apr 2028",
          "Forecast_Expires": "19 Jun 2028",
          "Predicted_Best_Buy_Date": "15 Jul 2026",
          "Predicted_Best_Buy_Price": 79.46,
          "Turnover_Cr": 172.11,
          "Fundamental_Risk": "Low",
          "Risk_Score": 13
        },
        {
          "Stock": "NLCINDIA.NS",
          "Company_Name": "NLC India Limited",
          "Band": "\u20b90\u2013\u20b9500",
          "Buy_Price": 303.55,
          "Shares": 18,
          "Invested": 5494.39,
          "Exit_Target": 337.38,
          "Exit_Value": 6072.84,
          "Gross_Profit": 608.94,
          "Net_Profit": 533.52,
          "Net_ROI_%": 9.71,
          "Best_Sell_Date": "16 May 2028",
          "Forecast_Expires": "19 Jun 2028",
          "Predicted_Best_Buy_Date": "15 Jul 2026",
          "Predicted_Best_Buy_Price": 303.6,
          "Turnover_Cr": 109.29,
          "Fundamental_Risk": "Low",
          "Risk_Score": 13
        }
      ]
    }
  ],
  "full_pool": [
    {
      "Price_Band": "\u20b90\u2013\u20b9500",
      "Stock": "GPIL.NS",
      "Company_Name": "Godawari Power & Ispat Limited",
      "Buy_Price": 251.25,
      "Exit_Target": 307.56,
      "Gross_ROI_%": 20.01,
      "After_Tax_ROI_%": 19.79,
      "Tax_Type": "LTCG",
      "Min_Hold_Until": "01 Jul 2027",
      "Best_Sell_Date": "03 Jan 2028",
      "Forecast_Expires": "03 Jan 2028",
      "Avg_Daily_Turnover_Cr": 32.54,
      "Sector": "Basic Materials",
      "Liquidity": "High",
      "Data_Days": 742,
      "Predicted_Best_Buy_Date": "17 Jul 2026",
      "Predicted_Best_Buy_Price": 248.67,
      "Fundamental_Risk": "Low",
      "Risk_Score": 7,
      "Risk_Reasons": "PE=20.0 within limit=55 (1.0\u00d7); D/E=0.08 within limit=3.25 (1.0\u00d7); Revenue growth=9.7% \u2192 0.90\u00d7; All 3 fields present (1.0\u00d7); ROE=14.9% \u2014 adequate (1.0\u00d7); EV/EBITDA=12.0x within limit=22x (1.0\u00d7); Earnings quality=1.45 \u2014 adequate (1.0\u00d7); Net Debt/EBITDA=-0.6x \u2014 net cash position (0.95\u00d7)"
    },
    {
      "Price_Band": "\u20b9500\u2013\u20b91000",
      "Stock": "NATCOPHARM.NS",
      "Company_Name": "NATCO Pharma Limited",
      "Buy_Price": 970.2,
      "Exit_Target": 1181.36,
      "Gross_ROI_%": 19.38,
      "After_Tax_ROI_%": 19.16,
      "Tax_Type": "LTCG",
      "Min_Hold_Until": "01 Jul 2027",
      "Best_Sell_Date": "01 Oct 2027",
      "Forecast_Expires": "01 Oct 2027",
      "Avg_Daily_Turnover_Cr": 64.53,
      "Sector": "Healthcare",
      "Liquidity": "High",
      "Data_Days": 742,
      "Predicted_Best_Buy_Date": "15 Jul 2026",
      "Predicted_Best_Buy_Price": 972.53,
      "Fundamental_Risk": "Medium",
      "Risk_Score": 38,
      "Risk_Reasons": "PE=12.2 within limit=50 (1.0\u00d7); D/E=0.08 within limit=2.75 (1.0\u00d7); Revenue growth=-39.6% \u2192 2.20\u00d7; All 3 fields present (1.0\u00d7); ROE=16.9% \u2014 adequate (1.0\u00d7); EV/EBITDA=11.2x within limit=25x (1.0\u00d7); Earnings quality=1.25 \u2014 adequate (1.0\u00d7); Net Debt/EBITDA=-1.0x \u2014 net cash position (0.95\u00d7)"
    },
    {
      "Price_Band": "\u20b90\u2013\u20b9500",
      "Stock": "TMCV.NS",
      "Company_Name": "TATA MOTORS LIMITED",
      "Buy_Price": 416.75,
      "Exit_Target": 476.54,
      "Gross_ROI_%": 12.11,
      "After_Tax_ROI_%": 11.89,
      "Tax_Type": "LTCG",
      "Min_Hold_Until": "01 Jul 2027",
      "Best_Sell_Date": "20 Oct 2027",
      "Forecast_Expires": "20 Oct 2027",
      "Avg_Daily_Turnover_Cr": 338.53,
      "Sector": "Consumer Cyclical",
      "Liquidity": "High",
      "Data_Days": 168,
      "Predicted_Best_Buy_Date": "23 Jul 2026",
      "Predicted_Best_Buy_Price": 415.1,
      "Fundamental_Risk": "High",
      "Risk_Score": 84,
      "Risk_Reasons": "PE=50.8 vs limit=25 \u2192 2.03\u00d7 (4.00\u00d7); D/E=0.44 within limit=2.55 (1.0\u00d7); Revenue growth=-37.8% \u2192 2.20\u00d7; All 3 fields present (1.0\u00d7); ROE=26.0% \u2014 strong (0.90\u00d7); EV/EBITDA=17.4x within limit=18x (1.0\u00d7); Earnings quality=4.94 \u2014 adequate (1.0\u00d7); Net Debt/EBITDA=-0.9x \u2014 net cash position (0.95\u00d7)"
    },
    {
      "Price_Band": "\u20b91000\u2013\u20b91500",
      "Stock": "PREMIERENE.NS",
      "Company_Name": "PREMIER ENERGIES LIMITED",
      "Buy_Price": 1100.0,
      "Exit_Target": 1223.82,
      "Gross_ROI_%": 9.08,
      "After_Tax_ROI_%": 8.87,
      "Tax_Type": "LTCG",
      "Min_Hold_Until": "01 Jul 2027",
      "Best_Sell_Date": "03 Jan 2028",
      "Forecast_Expires": "21 Jan 2028",
      "Avg_Daily_Turnover_Cr": 120.49,
      "Sector": "Technology",
      "Liquidity": "High",
      "Data_Days": 464,
      "Predicted_Best_Buy_Date": "07 Aug 2026",
      "Predicted_Best_Buy_Price": 1102.74,
      "Fundamental_Risk": "Low",
      "Risk_Score": 3,
      "Risk_Reasons": "PE=32.7 within limit=50 (1.0\u00d7); D/E=0.86 within limit=2.0 (1.0\u00d7); Revenue growth=37.6% \u2192 0.85\u00d7; All 3 fields present (1.0\u00d7); ROE=42.3% \u2014 strong (0.90\u00d7); EV/EBITDA=21.5x within limit=30x (1.0\u00d7); Earnings quality=0.84 \u2014 adequate (1.0\u00d7); Net Debt/EBITDA=0.5x within limit=3.5x (1.0\u00d7)"
    },
    {
      "Price_Band": "\u20b90\u2013\u20b9500",
      "Stock": "JINDALSAW.NS",
      "Company_Name": "Jindal Saw Limited",
      "Buy_Price": 267.3,
      "Exit_Target": 297.33,
      "Gross_ROI_%": 9.05,
      "After_Tax_ROI_%": 8.84,
      "Tax_Type": "LTCG",
      "Min_Hold_Until": "01 Jul 2027",
      "Best_Sell_Date": "12 Jun 2028",
      "Forecast_Expires": "19 Jun 2028",
      "Avg_Daily_Turnover_Cr": 46.58,
      "Sector": "Basic Materials",
      "Liquidity": "High",
      "Data_Days": 742,
      "Predicted_Best_Buy_Date": "21 Jul 2026",
      "Predicted_Best_Buy_Price": 267.83,
      "Fundamental_Risk": "Medium",
      "Risk_Score": 37,
      "Risk_Reasons": "PE=17.6 within limit=55 (1.0\u00d7); D/E=0.38 within limit=3.25 (1.0\u00d7); Revenue growth=-8.2% \u2192 1.58\u00d7; All 3 fields present (1.0\u00d7); ROE=8.0% \u2014 poor capital allocation (1.27\u00d7); EV/EBITDA=9.7x within limit=22x (1.0\u00d7); Earnings quality=1.82 \u2014 adequate (1.0\u00d7); Net Debt/EBITDA=1.9x within limit=3.5x (1.0\u00d7)"
    },
    {
      "Price_Band": "\u20b90\u2013\u20b9500",
      "Stock": "MAHABANK.NS",
      "Company_Name": "Bank of Maharashtra",
      "Buy_Price": 79.45,
      "Exit_Target": 88.37,
      "Gross_ROI_%": 9.05,
      "After_Tax_ROI_%": 8.84,
      "Tax_Type": "LTCG",
      "Min_Hold_Until": "01 Jul 2027",
      "Best_Sell_Date": "26 Apr 2028",
      "Forecast_Expires": "19 Jun 2028",
      "Avg_Daily_Turnover_Cr": 172.11,
      "Sector": "Financial Services",
      "Liquidity": "High",
      "Data_Days": 742,
      "Predicted_Best_Buy_Date": "15 Jul 2026",
      "Predicted_Best_Buy_Price": 79.46,
      "Fundamental_Risk": "Low",
      "Risk_Score": 13,
      "Risk_Reasons": "PE=8.3 within limit=22 (1.0\u00d7); D/E exempt \u2014 financial sector (1.0\u00d7); Revenue growth=21.8% \u2192 0.85\u00d7; 1 field(s) missing \u2192 1.2\u00d7; ROE=23.0% \u2014 acceptable (1.0\u00d7); EV/EBITDA unavailable \u2014 no multiplier; Earnings quality unavailable \u2014 no multiplier; Net Debt/EBITDA unavailable \u2014 no multiplier"
    },
    {
      "Price_Band": "\u20b90\u2013\u20b9500",
      "Stock": "THELEELA.NS",
      "Company_Name": "Leela Palaces Hotels & Resorts Limited",
      "Buy_Price": 491.45,
      "Exit_Target": 546.38,
      "Gross_ROI_%": 9.0,
      "After_Tax_ROI_%": 8.79,
      "Tax_Type": "LTCG",
      "Min_Hold_Until": "01 Jul 2027",
      "Best_Sell_Date": "12 Jun 2028",
      "Forecast_Expires": "19 Jun 2028",
      "Avg_Daily_Turnover_Cr": 27.64,
      "Sector": "Consumer Cyclical",
      "Liquidity": "High",
      "Data_Days": 279,
      "Predicted_Best_Buy_Date": "15 Jul 2026",
      "Predicted_Best_Buy_Price": 492.11,
      "Fundamental_Risk": "Low",
      "Risk_Score": 29,
      "Risk_Reasons": "PE=39.6 within limit=78 (1.0\u00d7); D/E=0.28 within limit=2.55 (1.0\u00d7); Revenue growth=8.2% \u2192 0.92\u00d7; All 3 fields present (1.0\u00d7); ROE=8.0% \u2014 poor capital allocation (1.26\u00d7); EV/EBITDA=24.4x vs limit=18x (1.39\u00d7); Earnings quality=1.93 \u2014 adequate (1.0\u00d7); Net Debt/EBITDA=2.0x within limit=3.5x (1.0\u00d7)"
    },
    {
      "Price_Band": "\u20b90\u2013\u20b9500",
      "Stock": "NLCINDIA.NS",
      "Company_Name": "NLC India Limited",
      "Buy_Price": 303.55,
      "Exit_Target": 337.38,
      "Gross_ROI_%": 8.97,
      "After_Tax_ROI_%": 8.76,
      "Tax_Type": "LTCG",
      "Min_Hold_Until": "01 Jul 2027",
      "Best_Sell_Date": "16 May 2028",
      "Forecast_Expires": "19 Jun 2028",
      "Avg_Daily_Turnover_Cr": 109.29,
      "Sector": "Utilities",
      "Liquidity": "High",
      "Data_Days": 742,
      "Predicted_Best_Buy_Date": "15 Jul 2026",
      "Predicted_Best_Buy_Price": 303.6,
      "Fundamental_Risk": "Low",
      "Risk_Score": 13,
      "Risk_Reasons": "PE=12.3 within limit=38 (1.0\u00d7); D/E=0.82 within limit=5.5 (1.0\u00d7); Revenue growth=-0.3% \u2192 1.01\u00d7; All 3 fields present (1.0\u00d7); ROE=16.0% \u2014 acceptable for utility (1.0\u00d7); EV/EBITDA=9.7x within limit=22x (1.0\u00d7); Earnings quality=1.47 \u2014 adequate (1.0\u00d7); Net Debt/EBITDA=2.0x within limit=6.0x (1.0\u00d7)"
    },
    {
      "Price_Band": "\u20b90\u2013\u20b9500",
      "Stock": "HINDCOPPER.NS",
      "Company_Name": "Hindustan Copper Limited",
      "Buy_Price": 490.0,
      "Exit_Target": 543.6,
      "Gross_ROI_%": 8.76,
      "After_Tax_ROI_%": 8.56,
      "Tax_Type": "LTCG",
      "Min_Hold_Until": "01 Jul 2027",
      "Best_Sell_Date": "15 Jul 2027",
      "Forecast_Expires": "06 Sep 2027",
      "Avg_Daily_Turnover_Cr": 169.02,
      "Sector": "Basic Materials",
      "Liquidity": "High",
      "Data_Days": 742,
      "Predicted_Best_Buy_Date": "25 Aug 2026",
      "Predicted_Best_Buy_Price": 487.12,
      "Fundamental_Risk": "Low",
      "Risk_Score": 17,
      "Risk_Reasons": "PE=51.5 within limit=55 (1.0\u00d7); D/E=0.03 within limit=3.25 (1.0\u00d7); Revenue growth=58.1% \u2192 0.85\u00d7; All 3 fields present (1.0\u00d7); ROE=30.6% \u2014 strong (0.90\u00d7); EV/EBITDA=32.5x vs limit=22x (1.57\u00d7); Earnings quality=1.60 \u2014 adequate (1.0\u00d7); Net Debt/EBITDA=-0.5x \u2014 net cash position (0.95\u00d7)"
    },
    {
      "Price_Band": "\u20b97000\u2013\u20b915000",
      "Stock": "OFSS.NS",
      "Company_Name": "Oracle Financial Services Software Limited",
      "Buy_Price": 11651.0,
      "Exit_Target": 12921.22,
      "Gross_ROI_%": 8.73,
      "After_Tax_ROI_%": 8.52,
      "Tax_Type": "LTCG",
      "Min_Hold_Until": "01 Jul 2027",
      "Best_Sell_Date": "12 Jan 2028",
      "Forecast_Expires": "12 Jan 2028",
      "Avg_Daily_Turnover_Cr": 346.83,
      "Sector": "Technology",
      "Liquidity": "High",
      "Data_Days": 742,
      "Predicted_Best_Buy_Date": "17 Jul 2026",
      "Predicted_Best_Buy_Price": 11653.99,
      "Fundamental_Risk": "Low",
      "Risk_Score": 1,
      "Risk_Reasons": "PE=38.3 within limit=65 (1.0\u00d7); D/E=0.00 within limit=2.0 (1.0\u00d7); Revenue growth=20.3% \u2192 0.85\u00d7; All 3 fields present (1.0\u00d7); ROE=32.6% \u2014 strong (0.90\u00d7); EV/EBITDA=28.0x within limit=30x (1.0\u00d7); Earnings quality=1.00 \u2014 adequate (1.0\u00d7); Net Debt/EBITDA=-1.6x \u2014 net cash position (0.95\u00d7)"
    },
    {
      "Price_Band": "\u20b90\u2013\u20b9500",
      "Stock": "IFCI.NS",
      "Company_Name": "IFCI Limited",
      "Buy_Price": 74.56,
      "Exit_Target": 82.65,
      "Gross_ROI_%": 8.68,
      "After_Tax_ROI_%": 8.47,
      "Tax_Type": "LTCG",
      "Min_Hold_Until": "01 Jul 2027",
      "Best_Sell_Date": "09 Feb 2028",
      "Forecast_Expires": "20 Mar 2028",
      "Avg_Daily_Turnover_Cr": 554.38,
      "Sector": "Financial Services",
      "Liquidity": "High",
      "Data_Days": 742,
      "Predicted_Best_Buy_Date": "15 Jul 2026",
      "Predicted_Best_Buy_Price": 74.61,
      "Fundamental_Risk": "High",
      "Risk_Score": 76,
      "Risk_Reasons": "PE=109.6 vs limit=45 \u2192 2.44\u00d7 (4.00\u00d7); D/E exempt \u2014 financial sector (1.0\u00d7); Revenue growth unavailable \u2014 no multiplier; 2 field(s) missing \u2192 1.5\u00d7; ROE unavailable \u2014 no multiplier; EV/EBITDA unavailable \u2014 no multiplier; Earnings quality unavailable \u2014 no multiplier; Net Debt/EBITDA unavailable \u2014 no multiplier"
    },
    {
      "Price_Band": "\u20b91500\u2013\u20b92000",
      "Stock": "IKS.NS",
      "Company_Name": "INVENTURUS KNOWLEDGE SO L",
      "Buy_Price": 1881.5,
      "Exit_Target": 2084.64,
      "Gross_ROI_%": 8.62,
      "After_Tax_ROI_%": 8.42,
      "Tax_Type": "LTCG",
      "Min_Hold_Until": "01 Jul 2027",
      "Best_Sell_Date": "25 Feb 2028",
      "Forecast_Expires": "19 Jun 2028",
      "Avg_Daily_Turnover_Cr": 56.14,
      "Sector": "Healthcare",
      "Liquidity": "High",
      "Data_Days": 389,
      "Predicted_Best_Buy_Date": "14 Aug 2026",
      "Predicted_Best_Buy_Price": 1862.76,
      "Fundamental_Risk": "Low",
      "Risk_Score": 8,
      "Risk_Reasons": "PE=44.6 within limit=76 (1.0\u00d7); D/E=0.27 within limit=2.75 (1.0\u00d7); Revenue growth=18.5% \u2192 0.85\u00d7; All 3 fields present (1.0\u00d7); ROE=31.4% \u2014 strong (0.90\u00d7); EV/EBITDA=29.3x vs limit=25x (1.15\u00d7); Earnings quality=0.93 \u2014 adequate (1.0\u00d7); Net Debt/EBITDA=0.1x within limit=3.5x (1.0\u00d7)"
    },
    {
      "Price_Band": "\u20b90\u2013\u20b9500",
      "Stock": "SARDAEN.NS",
      "Company_Name": "Sarda Energy & Minerals Limited",
      "Buy_Price": 493.2,
      "Exit_Target": 542.73,
      "Gross_ROI_%": 7.88,
      "After_Tax_ROI_%": 7.68,
      "Tax_Type": "LTCG",
      "Min_Hold_Until": "01 Jul 2027",
      "Best_Sell_Date": "15 May 2028",
      "Forecast_Expires": "19 Jun 2028",
      "Avg_Daily_Turnover_Cr": 12.88,
      "Sector": "Basic Materials",
      "Liquidity": "High",
      "Data_Days": 742,
      "Predicted_Best_Buy_Date": "15 Jul 2026",
      "Predicted_Best_Buy_Price": 493.03,
      "Fundamental_Risk": "Low",
      "Risk_Score": 13,
      "Risk_Reasons": "PE=15.7 within limit=55 (1.0\u00d7); D/E=0.35 within limit=3.25 (1.0\u00d7); Revenue growth=-0.6% \u2192 1.03\u00d7; All 3 fields present (1.0\u00d7); ROE=16.0% \u2014 adequate (1.0\u00d7); EV/EBITDA=10.1x within limit=22x (1.0\u00d7); Earnings quality=1.57 \u2014 adequate (1.0\u00d7); Net Debt/EBITDA=0.1x within limit=3.5x (1.0\u00d7)"
    },
    {
      "Price_Band": "Other",
      "Stock": "NEULANDLAB.NS",
      "Company_Name": "Neuland Laboratories Limited",
      "Buy_Price": 18999.0,
      "Exit_Target": 20929.14,
      "Gross_ROI_%": 8.0,
      "After_Tax_ROI_%": 7.59,
      "Tax_Type": "LTCG",
      "Min_Hold_Until": "01 Jul 2027",
      "Best_Sell_Date": "24 Feb 2028",
      "Forecast_Expires": "24 Feb 2028",
      "Avg_Daily_Turnover_Cr": 93.06,
      "Sector": "Healthcare",
      "Liquidity": "High",
      "Data_Days": 742,
      "Predicted_Best_Buy_Date": "29 Jul 2026",
      "Predicted_Best_Buy_Price": 18978.36,
      "Fundamental_Risk": "Medium",
      "Risk_Score": 60,
      "Risk_Reasons": "PE=67.0 vs limit=50 \u2192 1.34\u00d7 (1.60\u00d7); D/E=0.16 within limit=2.75 (1.0\u00d7); Revenue growth=136.4% \u2192 0.85\u00d7; All 3 fields present (1.0\u00d7); ROE unavailable \u2014 no multiplier; EV/EBITDA=456.1x vs limit=25x (3.00\u00d7); Earnings quality unavailable \u2014 no multiplier; Net Debt/EBITDA=-1.0x \u2014 net cash position (0.95\u00d7)"
    },
    {
      "Price_Band": "\u20b90\u2013\u20b9500",
      "Stock": "NATIONALUM.NS",
      "Company_Name": "National Aluminium Company Limited",
      "Buy_Price": 364.95,
      "Exit_Target": 401.19,
      "Gross_ROI_%": 7.77,
      "After_Tax_ROI_%": 7.57,
      "Tax_Type": "LTCG",
      "Min_Hold_Until": "01 Jul 2027",
      "Best_Sell_Date": "24 Mar 2028",
      "Forecast_Expires": "28 Apr 2028",
      "Avg_Daily_Turnover_Cr": 405.75,
      "Sector": "Basic Materials",
      "Liquidity": "High",
      "Data_Days": 742,
      "Predicted_Best_Buy_Date": "23 Jul 2026",
      "Predicted_Best_Buy_Price": 365.1,
      "Fundamental_Risk": "Low",
      "Risk_Score": 16,
      "Risk_Reasons": "PE=10.9 within limit=55 (1.0\u00d7); D/E=0.00 within limit=3.25 (1.0\u00d7); Revenue growth=-4.8% \u2192 1.31\u00d7; All 3 fields present (1.0\u00d7); ROE=29.4% \u2014 strong (0.90\u00d7); EV/EBITDA=7.1x within limit=22x (1.0\u00d7); Earnings quality=1.11 \u2014 adequate (1.0\u00d7); Net Debt/EBITDA=-1.1x \u2014 net cash position (0.95\u00d7)"
    },
    {
      "Price_Band": "\u20b92000\u2013\u20b92500",
      "Stock": "ANANDRATHI.NS",
      "Company_Name": "Anand Rathi Wealth Limited",
      "Buy_Price": 2082.0,
      "Exit_Target": 2288.22,
      "Gross_ROI_%": 7.75,
      "After_Tax_ROI_%": 7.54,
      "Tax_Type": "LTCG",
      "Min_Hold_Until": "01 Jul 2027",
      "Best_Sell_Date": "08 Nov 2027",
      "Forecast_Expires": "08 Nov 2027",
      "Avg_Daily_Turnover_Cr": 136.01,
      "Sector": "Financial Services",
      "Liquidity": "High",
      "Data_Days": 742,
      "Predicted_Best_Buy_Date": "15 Jul 2026",
      "Predicted_Best_Buy_Price": 2082.77,
      "Fundamental_Risk": "Medium",
      "Risk_Score": 39,
      "Risk_Reasons": "PE=75.2 vs limit=45 \u2192 1.67\u00d7 (2.65\u00d7); D/E exempt \u2014 financial sector (1.0\u00d7); Revenue growth=52.1% \u2192 0.85\u00d7; All 3 fields present (1.0\u00d7); ROE unavailable \u2014 no multiplier; EV/EBITDA exempt \u2014 financial sector (1.0\u00d7); Earnings quality unavailable \u2014 no multiplier; Net Debt/EBITDA=-0.6x \u2014 net cash position (0.95\u00d7)"
    }
  ]
}