{
  "date": "2026-07-17",
  "run_label": "Daily 2026-07-17",
  "run_time": "06:15",
  "results": {
    "\u20b90\u2013\u20b9500": [
      {
        "Price_Band": "\u20b90\u2013\u20b9500",
        "Stock": "GPIL.NS",
        "Company_Name": "Godawari Power & Ispat Limited",
        "Buy_Price": 242.95,
        "Exit_Target": 297.35,
        "Gross_ROI_%": 19.99,
        "After_Tax_ROI_%": 19.77,
        "Tax_Type": "LTCG",
        "Min_Hold_Until": "06 Jul 2027",
        "Best_Sell_Date": "05 Jan 2028",
        "Forecast_Expires": "05 Jan 2028",
        "Avg_Daily_Turnover_Cr": 28.43,
        "Sector": "Basic Materials",
        "Liquidity": "High",
        "Data_Days": 743,
        "Predicted_Best_Buy_Date": "20 Jul 2026",
        "Predicted_Best_Buy_Price": 239.19,
        "Fundamental_Risk": "Low",
        "Risk_Score": 7,
        "Risk_Reasons": "PE=19.3 within limit=55 (1.0\u00d7); D/E=0.08 within limit=3.25 (1.0\u00d7); Revenue growth=9.7% \u2192 0.90\u00d7; All 3 fields present (1.0\u00d7); ROE=14.9% \u2014 adequate (1.0\u00d7); EV/EBITDA=11.5x within limit=22x (1.0\u00d7); Earnings quality=1.45 \u2014 adequate (1.0\u00d7); Net Debt/EBITDA=-0.6x \u2014 net cash position (0.95\u00d7)"
      },
      {
        "Price_Band": "\u20b90\u2013\u20b9500",
        "Stock": "TMCV.NS",
        "Company_Name": "TATA MOTORS LIMITED",
        "Buy_Price": 415.15,
        "Exit_Target": 475.41,
        "Gross_ROI_%": 12.27,
        "After_Tax_ROI_%": 12.06,
        "Tax_Type": "LTCG",
        "Min_Hold_Until": "06 Jul 2027",
        "Best_Sell_Date": "25 Oct 2027",
        "Forecast_Expires": "25 Oct 2027",
        "Avg_Daily_Turnover_Cr": 331.16,
        "Sector": "Consumer Cyclical",
        "Liquidity": "High",
        "Data_Days": 171,
        "Predicted_Best_Buy_Date": "23 Jul 2026",
        "Predicted_Best_Buy_Price": 413.54,
        "Fundamental_Risk": "High",
        "Risk_Score": 84,
        "Risk_Reasons": "PE=51.9 vs limit=25 \u2192 2.08\u00d7 (4.00\u00d7); D/E=0.44 within limit=2.55 (1.0\u00d7); Revenue growth=-37.8% \u2192 2.20\u00d7; All 3 fields present (1.0\u00d7); ROE=26.0% \u2014 strong (0.90\u00d7); EV/EBITDA=17.0x within limit=18x (1.0\u00d7); Earnings quality=4.94 \u2014 adequate (1.0\u00d7); Net Debt/EBITDA=-0.9x \u2014 net cash position (0.95\u00d7)"
      },
      {
        "Price_Band": "\u20b90\u2013\u20b9500",
        "Stock": "JINDALSAW.NS",
        "Company_Name": "Jindal Saw Limited",
        "Buy_Price": 262.6,
        "Exit_Target": 294.59,
        "Gross_ROI_%": 9.98,
        "After_Tax_ROI_%": 9.77,
        "Tax_Type": "LTCG",
        "Min_Hold_Until": "06 Jul 2027",
        "Best_Sell_Date": "20 Jun 2028",
        "Forecast_Expires": "22 Jun 2028",
        "Avg_Daily_Turnover_Cr": 47.09,
        "Sector": "Basic Materials",
        "Liquidity": "High",
        "Data_Days": 743,
        "Predicted_Best_Buy_Date": "22 Jul 2026",
        "Predicted_Best_Buy_Price": 261.87,
        "Fundamental_Risk": "Low",
        "Risk_Score": 9,
        "Risk_Reasons": "PE=25.7 within limit=55 (1.0\u00d7); D/E=0.38 within limit=3.25 (1.0\u00d7); Revenue growth=9.0% \u2192 0.91\u00d7; All 3 fields present (1.0\u00d7); ROE unavailable \u2014 no multiplier; EV/EBITDA=11.1x within limit=22x (1.0\u00d7); Earnings quality unavailable \u2014 no multiplier; Net Debt/EBITDA=2.2x within limit=3.5x (1.0\u00d7)"
      },
      {
        "Price_Band": "\u20b90\u2013\u20b9500",
        "Stock": "NLCINDIA.NS",
        "Company_Name": "NLC India Limited",
        "Buy_Price": 296.2,
        "Exit_Target": 329.83,
        "Gross_ROI_%": 9.17,
        "After_Tax_ROI_%": 8.96,
        "Tax_Type": "LTCG",
        "Min_Hold_Until": "06 Jul 2027",
        "Best_Sell_Date": "24 May 2028",
        "Forecast_Expires": "22 Jun 2028",
        "Avg_Daily_Turnover_Cr": 94.07,
        "Sector": "Utilities",
        "Liquidity": "High",
        "Data_Days": 743,
        "Predicted_Best_Buy_Date": "24 Jul 2026",
        "Predicted_Best_Buy_Price": 296.59,
        "Fundamental_Risk": "Low",
        "Risk_Score": 13,
        "Risk_Reasons": "PE=11.7 within limit=38 (1.0\u00d7); D/E=0.82 within limit=5.5 (1.0\u00d7); Revenue growth=-0.3% \u2192 1.01\u00d7; All 3 fields present (1.0\u00d7); ROE=16.0% \u2014 acceptable for utility (1.0\u00d7); EV/EBITDA=9.6x within limit=22x (1.0\u00d7); Earnings quality=1.47 \u2014 adequate (1.0\u00d7); Net Debt/EBITDA=2.0x within limit=6.0x (1.0\u00d7)"
      },
      {
        "Price_Band": "\u20b90\u2013\u20b9500",
        "Stock": "MAHABANK.NS",
        "Company_Name": "Bank of Maharashtra",
        "Buy_Price": 79.56,
        "Exit_Target": 88.45,
        "Gross_ROI_%": 8.99,
        "After_Tax_ROI_%": 8.78,
        "Tax_Type": "LTCG",
        "Min_Hold_Until": "06 Jul 2027",
        "Best_Sell_Date": "01 May 2028",
        "Forecast_Expires": "22 Jun 2028",
        "Avg_Daily_Turnover_Cr": 163.42,
        "Sector": "Financial Services",
        "Liquidity": "High",
        "Data_Days": 743,
        "Predicted_Best_Buy_Date": "20 Jul 2026",
        "Predicted_Best_Buy_Price": 79.6,
        "Fundamental_Risk": "Low",
        "Risk_Score": 13,
        "Risk_Reasons": "PE=8.1 within limit=22 (1.0\u00d7); D/E exempt \u2014 financial sector (1.0\u00d7); Revenue growth=21.8% \u2192 0.85\u00d7; 1 field(s) missing \u2192 1.2\u00d7; ROE=23.0% \u2014 acceptable (1.0\u00d7); EV/EBITDA unavailable \u2014 no multiplier; Earnings quality unavailable \u2014 no multiplier; Net Debt/EBITDA unavailable \u2014 no multiplier"
      },
      {
        "Price_Band": "\u20b90\u2013\u20b9500",
        "Stock": "IFCI.NS",
        "Company_Name": "IFCI Limited",
        "Buy_Price": 71.66,
        "Exit_Target": 79.54,
        "Gross_ROI_%": 8.81,
        "After_Tax_ROI_%": 8.6,
        "Tax_Type": "LTCG",
        "Min_Hold_Until": "06 Jul 2027",
        "Best_Sell_Date": "14 Feb 2028",
        "Forecast_Expires": "21 Mar 2028",
        "Avg_Daily_Turnover_Cr": 242.21,
        "Sector": "Financial Services",
        "Liquidity": "High",
        "Data_Days": 744,
        "Predicted_Best_Buy_Date": "29 Jul 2026",
        "Predicted_Best_Buy_Price": 71.55,
        "Fundamental_Risk": "High",
        "Risk_Score": 76,
        "Risk_Reasons": "PE=105.4 vs limit=45 \u2192 2.34\u00d7 (4.00\u00d7); D/E exempt \u2014 financial sector (1.0\u00d7); Revenue growth unavailable \u2014 no multiplier; 2 field(s) missing \u2192 1.5\u00d7; ROE unavailable \u2014 no multiplier; EV/EBITDA unavailable \u2014 no multiplier; Earnings quality unavailable \u2014 no multiplier; Net Debt/EBITDA unavailable \u2014 no multiplier"
      },
      {
        "Price_Band": "\u20b90\u2013\u20b9500",
        "Stock": "HINDCOPPER.NS",
        "Company_Name": "Hindustan Copper Limited",
        "Buy_Price": 481.85,
        "Exit_Target": 534.68,
        "Gross_ROI_%": 8.79,
        "After_Tax_ROI_%": 8.58,
        "Tax_Type": "LTCG",
        "Min_Hold_Until": "06 Jul 2027",
        "Best_Sell_Date": "15 Jul 2027",
        "Forecast_Expires": "06 Sep 2027",
        "Avg_Daily_Turnover_Cr": 157.71,
        "Sector": "Basic Materials",
        "Liquidity": "High",
        "Data_Days": 744,
        "Predicted_Best_Buy_Date": "25 Aug 2026",
        "Predicted_Best_Buy_Price": 480.32,
        "Fundamental_Risk": "Low",
        "Risk_Score": 16,
        "Risk_Reasons": "PE=51.5 within limit=55 (1.0\u00d7); D/E=0.03 within limit=3.25 (1.0\u00d7); Revenue growth=58.1% \u2192 0.85\u00d7; All 3 fields present (1.0\u00d7); ROE=30.6% \u2014 strong (0.90\u00d7); EV/EBITDA=31.6x vs limit=22x (1.51\u00d7); Earnings quality=1.60 \u2014 adequate (1.0\u00d7); Net Debt/EBITDA=-0.5x \u2014 net cash position (0.95\u00d7)"
      }
    ],
    "\u20b9500\u2013\u20b91000": [
      {
        "Price_Band": "\u20b9500\u2013\u20b91000",
        "Stock": "NATCOPHARM.NS",
        "Company_Name": "NATCO Pharma Limited",
        "Buy_Price": 948.4,
        "Exit_Target": 1147.01,
        "Gross_ROI_%": 18.57,
        "After_Tax_ROI_%": 18.35,
        "Tax_Type": "LTCG",
        "Min_Hold_Until": "06 Jul 2027",
        "Best_Sell_Date": "20 Oct 2027",
        "Forecast_Expires": "20 Oct 2027",
        "Avg_Daily_Turnover_Cr": 57.31,
        "Sector": "Healthcare",
        "Liquidity": "High",
        "Data_Days": 744,
        "Predicted_Best_Buy_Date": "30 Jul 2026",
        "Predicted_Best_Buy_Price": 945.32,
        "Fundamental_Risk": "Medium",
        "Risk_Score": 38,
        "Risk_Reasons": "PE=12.0 within limit=50 (1.0\u00d7); D/E=0.08 within limit=2.75 (1.0\u00d7); Revenue growth=-39.6% \u2192 2.20\u00d7; All 3 fields present (1.0\u00d7); ROE=16.9% \u2014 adequate (1.0\u00d7); EV/EBITDA=11.1x within limit=25x (1.0\u00d7); Earnings quality=1.25 \u2014 adequate (1.0\u00d7); Net Debt/EBITDA=-1.0x \u2014 net cash position (0.95\u00d7)"
      }
    ],
    "\u20b91500\u2013\u20b92000": [
      {
        "Price_Band": "\u20b91500\u2013\u20b92000",
        "Stock": "IKS.NS",
        "Company_Name": "INVENTURUS KNOWLEDGE SO L",
        "Buy_Price": 1876.1,
        "Exit_Target": 2080.01,
        "Gross_ROI_%": 8.69,
        "After_Tax_ROI_%": 8.49,
        "Tax_Type": "LTCG",
        "Min_Hold_Until": "06 Jul 2027",
        "Best_Sell_Date": "29 Feb 2028",
        "Forecast_Expires": "22 Jun 2028",
        "Avg_Daily_Turnover_Cr": 55.83,
        "Sector": "Healthcare",
        "Liquidity": "High",
        "Data_Days": 391,
        "Predicted_Best_Buy_Date": "14 Aug 2026",
        "Predicted_Best_Buy_Price": 1859.05,
        "Fundamental_Risk": "Low",
        "Risk_Score": 7,
        "Risk_Reasons": "PE=44.4 within limit=76 (1.0\u00d7); D/E=0.27 within limit=2.75 (1.0\u00d7); Revenue growth=18.5% \u2192 0.85\u00d7; All 3 fields present (1.0\u00d7); ROE=31.4% \u2014 strong (0.90\u00d7); EV/EBITDA=28.7x vs limit=25x (1.13\u00d7); Earnings quality=0.93 \u2014 adequate (1.0\u00d7); Net Debt/EBITDA=0.1x within limit=3.5x (1.0\u00d7)"
      },
      {
        "Price_Band": "\u20b91500\u2013\u20b92000",
        "Stock": "AUROPHARMA.NS",
        "Company_Name": "Aurobindo Pharma Limited",
        "Buy_Price": 1535.6,
        "Exit_Target": 1693.08,
        "Gross_ROI_%": 8.09,
        "After_Tax_ROI_%": 7.89,
        "Tax_Type": "LTCG",
        "Min_Hold_Until": "06 Jul 2027",
        "Best_Sell_Date": "25 Nov 2027",
        "Forecast_Expires": "07 Dec 2027",
        "Avg_Daily_Turnover_Cr": 210.36,
        "Sector": "Healthcare",
        "Liquidity": "High",
        "Data_Days": 742,
        "Predicted_Best_Buy_Date": "23 Jul 2026",
        "Predicted_Best_Buy_Price": 1537.04,
        "Fundamental_Risk": "Low",
        "Risk_Score": 9,
        "Risk_Reasons": "PE=25.5 within limit=50 (1.0\u00d7); D/E=0.21 within limit=2.75 (1.0\u00d7); Revenue growth=5.6% \u2192 0.94\u00d7; All 3 fields present (1.0\u00d7); ROE=9.9% \u2014 poor capital allocation (1.00\u00d7); EV/EBITDA=12.7x within limit=25x (1.0\u00d7); Earnings quality=1.58 \u2014 adequate (1.0\u00d7); Net Debt/EBITDA=-0.4x \u2014 net cash position (0.95\u00d7)"
      }
    ],
    "\u20b97000\u2013\u20b915000": [
      {
        "Price_Band": "\u20b97000\u2013\u20b915000",
        "Stock": "POLYCAB.NS",
        "Company_Name": "Polycab India Limited",
        "Buy_Price": 8873.0,
        "Exit_Target": 9836.91,
        "Gross_ROI_%": 8.69,
        "After_Tax_ROI_%": 8.48,
        "Tax_Type": "LTCG",
        "Min_Hold_Until": "06 Jul 2027",
        "Best_Sell_Date": "21 Jun 2028",
        "Forecast_Expires": "22 Jun 2028",
        "Avg_Daily_Turnover_Cr": 369.21,
        "Sector": "Industrials",
        "Liquidity": "High",
        "Data_Days": 744,
        "Predicted_Best_Buy_Date": "29 Jul 2026",
        "Predicted_Best_Buy_Price": 8870.4,
        "Fundamental_Risk": "Low",
        "Risk_Score": 18,
        "Risk_Reasons": "PE=50.7 within limit=60 (1.0\u00d7); D/E=0.03 within limit=3.5 (1.0\u00d7); Revenue growth=26.9% \u2192 0.85\u00d7; All 3 fields present (1.0\u00d7); ROE=24.6% \u2014 strong (0.90\u00d7); EV/EBITDA=33.2x vs limit=22x (1.62\u00d7); Earnings quality=1.43 \u2014 adequate (1.0\u00d7); Net Debt/EBITDA=-0.9x \u2014 net cash position (0.95\u00d7)"
      },
      {
        "Price_Band": "\u20b97000\u2013\u20b915000",
        "Stock": "OFSS.NS",
        "Company_Name": "Oracle Financial Services Software Limited",
        "Buy_Price": 11619.0,
        "Exit_Target": 12849.37,
        "Gross_ROI_%": 8.42,
        "After_Tax_ROI_%": 8.21,
        "Tax_Type": "LTCG",
        "Min_Hold_Until": "06 Jul 2027",
        "Best_Sell_Date": "20 Jan 2028",
        "Forecast_Expires": "20 Jan 2028",
        "Avg_Daily_Turnover_Cr": 359.3,
        "Sector": "Technology",
        "Liquidity": "High",
        "Data_Days": 743,
        "Predicted_Best_Buy_Date": "20 Jul 2026",
        "Predicted_Best_Buy_Price": 11612.21,
        "Fundamental_Risk": "Low",
        "Risk_Score": 1,
        "Risk_Reasons": "PE=38.4 within limit=65 (1.0\u00d7); D/E=0.00 within limit=2.0 (1.0\u00d7); Revenue growth=20.3% \u2192 0.85\u00d7; All 3 fields present (1.0\u00d7); ROE=32.6% \u2014 strong (0.90\u00d7); EV/EBITDA=27.8x within limit=30x (1.0\u00d7); Earnings quality=1.00 \u2014 adequate (1.0\u00d7); Net Debt/EBITDA=-1.6x \u2014 net cash position (0.95\u00d7)"
      }
    ]
  },
  "portfolios": [
    {
      "name": "Best Overall (Composite Score)",
      "description": "Highest composite score: ROI \u00d7 liquidity \u00d7 sell month \u00d7 risk penalty \u2014 most well-rounded",
      "summary": {
        "Total_Invested": 43052.67,
        "Total_Net_Profit": 6059.35,
        "Portfolio_ROI_%": 14.07,
        "Earliest_Sell": "05 Jan 2028",
        "Latest_Sell": "29 Feb 2028",
        "Num_Stocks": 5,
        "Risk_Breakdown": {
          "Low": 4,
          "Medium": 1
        }
      },
      "portfolio": [
        {
          "Stock": "GPIL.NS",
          "Company_Name": "Godawari Power & Ispat Limited",
          "Band": "\u20b90\u2013\u20b9500",
          "Buy_Price": 242.95,
          "Shares": 39,
          "Invested": 9528.41,
          "Exit_Target": 297.35,
          "Exit_Value": 11596.65,
          "Gross_Profit": 2121.6,
          "Net_Profit": 1983.39,
          "Net_ROI_%": 20.82,
          "Best_Sell_Date": "05 Jan 2028",
          "Forecast_Expires": "05 Jan 2028",
          "Predicted_Best_Buy_Date": "20 Jul 2026",
          "Predicted_Best_Buy_Price": 239.19,
          "Turnover_Cr": 28.43,
          "Fundamental_Risk": "Low",
          "Risk_Score": 7
        },
        {
          "Stock": "NATCOPHARM.NS",
          "Company_Name": "NATCO Pharma Limited",
          "Band": "\u20b9500\u2013\u20b91000",
          "Buy_Price": 948.4,
          "Shares": 10,
          "Invested": 9537.36,
          "Exit_Target": 1147.01,
          "Exit_Value": 11470.1,
          "Gross_Profit": 1986.1,
          "Net_Profit": 1848.7,
          "Net_ROI_%": 19.38,
          "Best_Sell_Date": "20 Oct 2027",
          "Forecast_Expires": "20 Oct 2027",
          "Predicted_Best_Buy_Date": "30 Jul 2026",
          "Predicted_Best_Buy_Price": 945.32,
          "Turnover_Cr": 57.31,
          "Fundamental_Risk": "Medium",
          "Risk_Score": 38
        },
        {
          "Stock": "AUROPHARMA.NS",
          "Company_Name": "Aurobindo Pharma Limited",
          "Band": "\u20b91500\u2013\u20b92000",
          "Buy_Price": 1535.6,
          "Shares": 5,
          "Invested": 7720.23,
          "Exit_Target": 1693.08,
          "Exit_Value": 8465.4,
          "Gross_Profit": 787.4,
          "Net_Profit": 682.47,
          "Net_ROI_%": 8.84,
          "Best_Sell_Date": "25 Nov 2027",
          "Forecast_Expires": "07 Dec 2027",
          "Predicted_Best_Buy_Date": "23 Jul 2026",
          "Predicted_Best_Buy_Price": 1537.04,
          "Turnover_Cr": 210.36,
          "Fundamental_Risk": "Low",
          "Risk_Score": 9
        },
        {
          "Stock": "HINDCOPPER.NS",
          "Company_Name": "Hindustan Copper Limited",
          "Band": "\u20b90\u2013\u20b9500",
          "Buy_Price": 481.85,
          "Shares": 18,
          "Invested": 8721.0,
          "Exit_Target": 534.68,
          "Exit_Value": 9624.24,
          "Gross_Profit": 950.94,
          "Net_Profit": 832.01,
          "Net_ROI_%": 9.54,
          "Best_Sell_Date": "15 Jul 2027",
          "Forecast_Expires": "06 Sep 2027",
          "Predicted_Best_Buy_Date": "25 Aug 2026",
          "Predicted_Best_Buy_Price": 480.32,
          "Turnover_Cr": 157.71,
          "Fundamental_Risk": "Low",
          "Risk_Score": 16
        },
        {
          "Stock": "IKS.NS",
          "Company_Name": "INVENTURUS KNOWLEDGE SO L",
          "Band": "\u20b91500\u2013\u20b92000",
          "Buy_Price": 1876.1,
          "Shares": 4,
          "Invested": 7545.67,
          "Exit_Target": 2080.01,
          "Exit_Value": 8320.04,
          "Gross_Profit": 815.64,
          "Net_Profit": 712.78,
          "Net_ROI_%": 9.45,
          "Best_Sell_Date": "29 Feb 2028",
          "Forecast_Expires": "22 Jun 2028",
          "Predicted_Best_Buy_Date": "14 Aug 2026",
          "Predicted_Best_Buy_Price": 1859.05,
          "Turnover_Cr": 55.83,
          "Fundamental_Risk": "Low",
          "Risk_Score": 7
        }
      ]
    },
    {
      "name": "Max After-Tax Return",
      "description": "Top stocks by after-tax ROI \u2014 highest yield, check Risk column for each stock",
      "summary": {
        "Total_Invested": 49522.43,
        "Total_Net_Profit": 7265.24,
        "Portfolio_ROI_%": 14.67,
        "Earliest_Sell": "01 May 2028",
        "Latest_Sell": "25 Oct 2027",
        "Num_Stocks": 7,
        "Risk_Breakdown": {
          "Low": 4,
          "High": 2,
          "Medium": 1
        }
      },
      "portfolio": [
        {
          "Stock": "GPIL.NS",
          "Company_Name": "Godawari Power & Ispat Limited",
          "Band": "\u20b90\u2013\u20b9500",
          "Buy_Price": 242.95,
          "Shares": 43,
          "Invested": 10504.65,
          "Exit_Target": 297.35,
          "Exit_Value": 12786.05,
          "Gross_Profit": 2339.2,
          "Net_Profit": 2187.85,
          "Net_ROI_%": 20.83,
          "Best_Sell_Date": "05 Jan 2028",
          "Forecast_Expires": "05 Jan 2028",
          "Predicted_Best_Buy_Date": "20 Jul 2026",
          "Predicted_Best_Buy_Price": 239.19,
          "Turnover_Cr": 28.43,
          "Fundamental_Risk": "Low",
          "Risk_Score": 7
        },
        {
          "Stock": "NATCOPHARM.NS",
          "Company_Name": "NATCO Pharma Limited",
          "Band": "\u20b9500\u2013\u20b91000",
          "Buy_Price": 948.4,
          "Shares": 11,
          "Invested": 10490.2,
          "Exit_Target": 1147.01,
          "Exit_Value": 12617.11,
          "Gross_Profit": 2184.71,
          "Net_Profit": 2034.47,
          "Net_ROI_%": 19.39,
          "Best_Sell_Date": "20 Oct 2027",
          "Forecast_Expires": "20 Oct 2027",
          "Predicted_Best_Buy_Date": "30 Jul 2026",
          "Predicted_Best_Buy_Price": 945.32,
          "Turnover_Cr": 57.31,
          "Fundamental_Risk": "Medium",
          "Risk_Score": 38
        },
        {
          "Stock": "TMCV.NS",
          "Company_Name": "TATA MOTORS LIMITED",
          "Band": "\u20b90\u2013\u20b9500",
          "Buy_Price": 415.15,
          "Shares": 14,
          "Invested": 5845.1,
          "Exit_Target": 475.41,
          "Exit_Value": 6655.74,
          "Gross_Profit": 843.64,
          "Net_Profit": 761.57,
          "Net_ROI_%": 13.03,
          "Best_Sell_Date": "25 Oct 2027",
          "Forecast_Expires": "25 Oct 2027",
          "Predicted_Best_Buy_Date": "23 Jul 2026",
          "Predicted_Best_Buy_Price": 413.54,
          "Turnover_Cr": 331.16,
          "Fundamental_Risk": "High",
          "Risk_Score": 84
        },
        {
          "Stock": "JINDALSAW.NS",
          "Company_Name": "Jindal Saw Limited",
          "Band": "\u20b90\u2013\u20b9500",
          "Buy_Price": 262.6,
          "Shares": 26,
          "Invested": 6865.44,
          "Exit_Target": 294.59,
          "Exit_Value": 7659.34,
          "Gross_Profit": 831.74,
          "Net_Profit": 737.28,
          "Net_ROI_%": 10.74,
          "Best_Sell_Date": "20 Jun 2028",
          "Forecast_Expires": "22 Jun 2028",
          "Predicted_Best_Buy_Date": "22 Jul 2026",
          "Predicted_Best_Buy_Price": 261.87,
          "Turnover_Cr": 47.09,
          "Fundamental_Risk": "Low",
          "Risk_Score": 9
        },
        {
          "Stock": "NLCINDIA.NS",
          "Company_Name": "NLC India Limited",
          "Band": "\u20b90\u2013\u20b9500",
          "Buy_Price": 296.2,
          "Shares": 20,
          "Invested": 5958.07,
          "Exit_Target": 329.83,
          "Exit_Value": 6596.6,
          "Gross_Profit": 672.6,
          "Net_Profit": 589.73,
          "Net_ROI_%": 9.9,
          "Best_Sell_Date": "24 May 2028",
          "Forecast_Expires": "22 Jun 2028",
          "Predicted_Best_Buy_Date": "24 Jul 2026",
          "Predicted_Best_Buy_Price": 296.59,
          "Turnover_Cr": 94.07,
          "Fundamental_Risk": "Low",
          "Risk_Score": 13
        },
        {
          "Stock": "MAHABANK.NS",
          "Company_Name": "Bank of Maharashtra",
          "Band": "\u20b90\u2013\u20b9500",
          "Buy_Price": 79.56,
          "Shares": 80,
          "Invested": 6400.15,
          "Exit_Target": 88.45,
          "Exit_Value": 7076.0,
          "Gross_Profit": 711.2,
          "Net_Profit": 623.49,
          "Net_ROI_%": 9.74,
          "Best_Sell_Date": "01 May 2028",
          "Forecast_Expires": "22 Jun 2028",
          "Predicted_Best_Buy_Date": "20 Jul 2026",
          "Predicted_Best_Buy_Price": 79.6,
          "Turnover_Cr": 163.42,
          "Fundamental_Risk": "Low",
          "Risk_Score": 13
        },
        {
          "Stock": "IFCI.NS",
          "Company_Name": "IFCI Limited",
          "Band": "\u20b90\u2013\u20b9500",
          "Buy_Price": 71.66,
          "Shares": 48,
          "Invested": 3458.82,
          "Exit_Target": 79.54,
          "Exit_Value": 3817.92,
          "Gross_Profit": 378.24,
          "Net_Profit": 330.85,
          "Net_ROI_%": 9.57,
          "Best_Sell_Date": "14 Feb 2028",
          "Forecast_Expires": "21 Mar 2028",
          "Predicted_Best_Buy_Date": "29 Jul 2026",
          "Predicted_Best_Buy_Price": 71.55,
          "Turnover_Cr": 242.21,
          "Fundamental_Risk": "High",
          "Risk_Score": 76
        }
      ]
    },
    {
      "name": "Balanced Cap Mix",
      "description": "4 each from small / mid / large cap \u2014 diversified across market cap segments",
      "summary": {
        "Total_Invested": 36240.68,
        "Total_Net_Profit": 4389.77,
        "Portfolio_ROI_%": 12.11,
        "Earliest_Sell": "20 Oct 2027",
        "Latest_Sell": "29 Feb 2028",
        "Num_Stocks": 4,
        "Risk_Breakdown": {
          "Low": 3,
          "Medium": 1
        }
      },
      "portfolio": [
        {
          "Stock": "NATCOPHARM.NS",
          "Company_Name": "NATCO Pharma Limited",
          "Band": "\u20b9500\u2013\u20b91000",
          "Buy_Price": 948.4,
          "Shares": 11,
          "Invested": 10490.11,
          "Exit_Target": 1147.01,
          "Exit_Value": 12617.11,
          "Gross_Profit": 2184.71,
          "Net_Profit": 2034.55,
          "Net_ROI_%": 19.39,
          "Best_Sell_Date": "20 Oct 2027",
          "Forecast_Expires": "20 Oct 2027",
          "Predicted_Best_Buy_Date": "30 Jul 2026",
          "Predicted_Best_Buy_Price": 945.32,
          "Turnover_Cr": 57.31,
          "Fundamental_Risk": "Medium",
          "Risk_Score": 38
        },
        {
          "Stock": "AUROPHARMA.NS",
          "Company_Name": "Aurobindo Pharma Limited",
          "Band": "\u20b91500\u2013\u20b92000",
          "Buy_Price": 1535.6,
          "Shares": 6,
          "Invested": 9271.31,
          "Exit_Target": 1693.08,
          "Exit_Value": 10158.48,
          "Gross_Profit": 944.88,
          "Net_Profit": 811.92,
          "Net_ROI_%": 8.76,
          "Best_Sell_Date": "25 Nov 2027",
          "Forecast_Expires": "07 Dec 2027",
          "Predicted_Best_Buy_Date": "23 Jul 2026",
          "Predicted_Best_Buy_Price": 1537.04,
          "Turnover_Cr": 210.36,
          "Fundamental_Risk": "Low",
          "Risk_Score": 9
        },
        {
          "Stock": "IKS.NS",
          "Company_Name": "INVENTURUS KNOWLEDGE SO L",
          "Band": "\u20b91500\u2013\u20b92000",
          "Buy_Price": 1876.1,
          "Shares": 4,
          "Invested": 7555.84,
          "Exit_Target": 2080.01,
          "Exit_Value": 8320.04,
          "Gross_Profit": 815.64,
          "Net_Profit": 702.62,
          "Net_ROI_%": 9.3,
          "Best_Sell_Date": "29 Feb 2028",
          "Forecast_Expires": "22 Jun 2028",
          "Predicted_Best_Buy_Date": "14 Aug 2026",
          "Predicted_Best_Buy_Price": 1859.05,
          "Turnover_Cr": 55.83,
          "Fundamental_Risk": "Low",
          "Risk_Score": 7
        },
        {
          "Stock": "POLYCAB.NS",
          "Company_Name": "Polycab India Limited",
          "Band": "\u20b97000\u2013\u20b915000",
          "Buy_Price": 8873.0,
          "Shares": 1,
          "Invested": 8923.42,
          "Exit_Target": 9836.91,
          "Exit_Value": 9836.91,
          "Gross_Profit": 963.91,
          "Net_Profit": 840.68,
          "Net_ROI_%": 9.42,
          "Best_Sell_Date": "21 Jun 2028",
          "Forecast_Expires": "22 Jun 2028",
          "Predicted_Best_Buy_Date": "29 Jul 2026",
          "Predicted_Best_Buy_Price": 8870.4,
          "Turnover_Cr": 369.21,
          "Fundamental_Risk": "Low",
          "Risk_Score": 18
        }
      ]
    },
    {
      "name": "High Liquidity",
      "description": "Top stocks by daily turnover \u2014 easiest to exit without moving the price",
      "summary": {
        "Total_Invested": 43179.63,
        "Total_Net_Profit": 4388.1,
        "Portfolio_ROI_%": 10.16,
        "Earliest_Sell": "01 May 2028",
        "Latest_Sell": "25 Oct 2027",
        "Num_Stocks": 5,
        "Risk_Breakdown": {
          "Low": 3,
          "High": 2
        }
      },
      "portfolio": [
        {
          "Stock": "TMCV.NS",
          "Company_Name": "TATA MOTORS LIMITED",
          "Band": "\u20b90\u2013\u20b9500",
          "Buy_Price": 415.15,
          "Shares": 21,
          "Invested": 8766.1,
          "Exit_Target": 475.41,
          "Exit_Value": 9983.61,
          "Gross_Profit": 1265.46,
          "Net_Profit": 1143.9,
          "Net_ROI_%": 13.05,
          "Best_Sell_Date": "25 Oct 2027",
          "Forecast_Expires": "25 Oct 2027",
          "Predicted_Best_Buy_Date": "23 Jul 2026",
          "Predicted_Best_Buy_Price": 413.54,
          "Turnover_Cr": 331.16,
          "Fundamental_Risk": "High",
          "Risk_Score": 84
        },
        {
          "Stock": "IFCI.NS",
          "Company_Name": "IFCI Limited",
          "Band": "\u20b90\u2013\u20b9500",
          "Buy_Price": 71.66,
          "Shares": 125,
          "Invested": 9006.77,
          "Exit_Target": 79.54,
          "Exit_Value": 9942.5,
          "Gross_Profit": 985.0,
          "Net_Profit": 862.15,
          "Net_ROI_%": 9.57,
          "Best_Sell_Date": "14 Feb 2028",
          "Forecast_Expires": "21 Mar 2028",
          "Predicted_Best_Buy_Date": "29 Jul 2026",
          "Predicted_Best_Buy_Price": 71.55,
          "Turnover_Cr": 242.21,
          "Fundamental_Risk": "High",
          "Risk_Score": 76
        },
        {
          "Stock": "AUROPHARMA.NS",
          "Company_Name": "Aurobindo Pharma Limited",
          "Band": "\u20b91500\u2013\u20b92000",
          "Buy_Price": 1535.6,
          "Shares": 5,
          "Invested": 7726.03,
          "Exit_Target": 1693.08,
          "Exit_Value": 8465.4,
          "Gross_Profit": 787.4,
          "Net_Profit": 676.67,
          "Net_ROI_%": 8.76,
          "Best_Sell_Date": "25 Nov 2027",
          "Forecast_Expires": "07 Dec 2027",
          "Predicted_Best_Buy_Date": "23 Jul 2026",
          "Predicted_Best_Buy_Price": 1537.04,
          "Turnover_Cr": 210.36,
          "Fundamental_Risk": "Low",
          "Risk_Score": 9
        },
        {
          "Stock": "MAHABANK.NS",
          "Company_Name": "Bank of Maharashtra",
          "Band": "\u20b90\u2013\u20b9500",
          "Buy_Price": 79.56,
          "Shares": 112,
          "Invested": 8959.73,
          "Exit_Target": 88.45,
          "Exit_Value": 9906.4,
          "Gross_Profit": 995.68,
          "Net_Profit": 873.37,
          "Net_ROI_%": 9.75,
          "Best_Sell_Date": "01 May 2028",
          "Forecast_Expires": "22 Jun 2028",
          "Predicted_Best_Buy_Date": "20 Jul 2026",
          "Predicted_Best_Buy_Price": 79.6,
          "Turnover_Cr": 163.42,
          "Fundamental_Risk": "Low",
          "Risk_Score": 13
        },
        {
          "Stock": "HINDCOPPER.NS",
          "Company_Name": "Hindustan Copper Limited",
          "Band": "\u20b90\u2013\u20b9500",
          "Buy_Price": 481.85,
          "Shares": 18,
          "Invested": 8721.0,
          "Exit_Target": 534.68,
          "Exit_Value": 9624.24,
          "Gross_Profit": 950.94,
          "Net_Profit": 832.01,
          "Net_ROI_%": 9.54,
          "Best_Sell_Date": "15 Jul 2027",
          "Forecast_Expires": "06 Sep 2027",
          "Predicted_Best_Buy_Date": "25 Aug 2026",
          "Predicted_Best_Buy_Price": 480.32,
          "Turnover_Cr": 157.71,
          "Fundamental_Risk": "Low",
          "Risk_Score": 16
        }
      ]
    },
    {
      "name": "Mid-2027 Exit (Jul\u2013Oct)",
      "description": "Peaks Jul\u2013Oct 2027 \u2014 exit before year-end, redeploy for next cycle early",
      "summary": {
        "Total_Invested": 48971.56,
        "Total_Net_Profit": 6833.62,
        "Portfolio_ROI_%": 13.95,
        "Earliest_Sell": "15 Jul 2027",
        "Latest_Sell": "25 Oct 2027",
        "Num_Stocks": 3,
        "Risk_Breakdown": {
          "Medium": 1,
          "High": 1,
          "Low": 1
        }
      },
      "portfolio": [
        {
          "Stock": "NATCOPHARM.NS",
          "Company_Name": "NATCO Pharma Limited",
          "Band": "\u20b9500\u2013\u20b91000",
          "Buy_Price": 948.4,
          "Shares": 17,
          "Invested": 16214.47,
          "Exit_Target": 1147.01,
          "Exit_Value": 19499.17,
          "Gross_Profit": 3376.37,
          "Net_Profit": 3141.84,
          "Net_ROI_%": 19.38,
          "Best_Sell_Date": "20 Oct 2027",
          "Forecast_Expires": "20 Oct 2027",
          "Predicted_Best_Buy_Date": "30 Jul 2026",
          "Predicted_Best_Buy_Price": 945.32,
          "Turnover_Cr": 57.31,
          "Fundamental_Risk": "Medium",
          "Risk_Score": 38
        },
        {
          "Stock": "TMCV.NS",
          "Company_Name": "TATA MOTORS LIMITED",
          "Band": "\u20b90\u2013\u20b9500",
          "Buy_Price": 415.15,
          "Shares": 39,
          "Invested": 16282.52,
          "Exit_Target": 475.41,
          "Exit_Value": 18540.99,
          "Gross_Profit": 2350.14,
          "Net_Profit": 2121.77,
          "Net_ROI_%": 13.03,
          "Best_Sell_Date": "25 Oct 2027",
          "Forecast_Expires": "25 Oct 2027",
          "Predicted_Best_Buy_Date": "23 Jul 2026",
          "Predicted_Best_Buy_Price": 413.54,
          "Turnover_Cr": 331.16,
          "Fundamental_Risk": "High",
          "Risk_Score": 84
        },
        {
          "Stock": "HINDCOPPER.NS",
          "Company_Name": "Hindustan Copper Limited",
          "Band": "\u20b90\u2013\u20b9500",
          "Buy_Price": 481.85,
          "Shares": 34,
          "Invested": 16474.57,
          "Exit_Target": 534.68,
          "Exit_Value": 18179.12,
          "Gross_Profit": 1796.22,
          "Net_Profit": 1570.01,
          "Net_ROI_%": 9.53,
          "Best_Sell_Date": "15 Jul 2027",
          "Forecast_Expires": "06 Sep 2027",
          "Predicted_Best_Buy_Date": "25 Aug 2026",
          "Predicted_Best_Buy_Price": 480.32,
          "Turnover_Cr": 157.71,
          "Fundamental_Risk": "Low",
          "Risk_Score": 16
        }
      ]
    },
    {
      "name": "Patient Hold (2028 exit)",
      "description": "Peaks in 2028 \u2014 maximum LTCG window, full mean reversion cycle",
      "summary": {
        "Total_Invested": 50011.09,
        "Total_Net_Profit": 6083.91,
        "Portfolio_ROI_%": 12.17,
        "Earliest_Sell": "01 May 2028",
        "Latest_Sell": "29 Feb 2028",
        "Num_Stocks": 6,
        "Risk_Breakdown": {
          "Low": 5,
          "High": 1
        }
      },
      "portfolio": [
        {
          "Stock": "GPIL.NS",
          "Company_Name": "Godawari Power & Ispat Limited",
          "Band": "\u20b90\u2013\u20b9500",
          "Buy_Price": 242.95,
          "Shares": 42,
          "Invested": 10260.71,
          "Exit_Target": 297.35,
          "Exit_Value": 12488.7,
          "Gross_Profit": 2284.8,
          "Net_Profit": 2136.61,
          "Net_ROI_%": 20.82,
          "Best_Sell_Date": "05 Jan 2028",
          "Forecast_Expires": "05 Jan 2028",
          "Predicted_Best_Buy_Date": "20 Jul 2026",
          "Predicted_Best_Buy_Price": 239.19,
          "Turnover_Cr": 28.43,
          "Fundamental_Risk": "Low",
          "Risk_Score": 7
        },
        {
          "Stock": "JINDALSAW.NS",
          "Company_Name": "Jindal Saw Limited",
          "Band": "\u20b90\u2013\u20b9500",
          "Buy_Price": 262.6,
          "Shares": 34,
          "Invested": 8977.51,
          "Exit_Target": 294.59,
          "Exit_Value": 10016.06,
          "Gross_Profit": 1087.66,
          "Net_Profit": 964.52,
          "Net_ROI_%": 10.74,
          "Best_Sell_Date": "20 Jun 2028",
          "Forecast_Expires": "22 Jun 2028",
          "Predicted_Best_Buy_Date": "22 Jul 2026",
          "Predicted_Best_Buy_Price": 261.87,
          "Turnover_Cr": 47.09,
          "Fundamental_Risk": "Low",
          "Risk_Score": 9
        },
        {
          "Stock": "NLCINDIA.NS",
          "Company_Name": "NLC India Limited",
          "Band": "\u20b90\u2013\u20b9500",
          "Buy_Price": 296.2,
          "Shares": 30,
          "Invested": 8934.87,
          "Exit_Target": 329.83,
          "Exit_Value": 9894.9,
          "Gross_Profit": 1008.9,
          "Net_Profit": 886.82,
          "Net_ROI_%": 9.93,
          "Best_Sell_Date": "24 May 2028",
          "Forecast_Expires": "22 Jun 2028",
          "Predicted_Best_Buy_Date": "24 Jul 2026",
          "Predicted_Best_Buy_Price": 296.59,
          "Turnover_Cr": 94.07,
          "Fundamental_Risk": "Low",
          "Risk_Score": 13
        },
        {
          "Stock": "MAHABANK.NS",
          "Company_Name": "Bank of Maharashtra",
          "Band": "\u20b90\u2013\u20b9500",
          "Buy_Price": 79.56,
          "Shares": 112,
          "Invested": 8959.73,
          "Exit_Target": 88.45,
          "Exit_Value": 9906.4,
          "Gross_Profit": 995.68,
          "Net_Profit": 873.37,
          "Net_ROI_%": 9.75,
          "Best_Sell_Date": "01 May 2028",
          "Forecast_Expires": "22 Jun 2028",
          "Predicted_Best_Buy_Date": "20 Jul 2026",
          "Predicted_Best_Buy_Price": 79.6,
          "Turnover_Cr": 163.42,
          "Fundamental_Risk": "Low",
          "Risk_Score": 13
        },
        {
          "Stock": "IFCI.NS",
          "Company_Name": "IFCI Limited",
          "Band": "\u20b90\u2013\u20b9500",
          "Buy_Price": 71.66,
          "Shares": 74,
          "Invested": 5332.01,
          "Exit_Target": 79.54,
          "Exit_Value": 5885.96,
          "Gross_Profit": 583.12,
          "Net_Profit": 510.39,
          "Net_ROI_%": 9.57,
          "Best_Sell_Date": "14 Feb 2028",
          "Forecast_Expires": "21 Mar 2028",
          "Predicted_Best_Buy_Date": "29 Jul 2026",
          "Predicted_Best_Buy_Price": 71.55,
          "Turnover_Cr": 242.21,
          "Fundamental_Risk": "High",
          "Risk_Score": 76
        },
        {
          "Stock": "IKS.NS",
          "Company_Name": "INVENTURUS KNOWLEDGE SO L",
          "Band": "\u20b91500\u2013\u20b92000",
          "Buy_Price": 1876.1,
          "Shares": 4,
          "Invested": 7546.26,
          "Exit_Target": 2080.01,
          "Exit_Value": 8320.04,
          "Gross_Profit": 815.64,
          "Net_Profit": 712.2,
          "Net_ROI_%": 9.44,
          "Best_Sell_Date": "29 Feb 2028",
          "Forecast_Expires": "22 Jun 2028",
          "Predicted_Best_Buy_Date": "14 Aug 2026",
          "Predicted_Best_Buy_Price": 1859.05,
          "Turnover_Cr": 55.83,
          "Fundamental_Risk": "Low",
          "Risk_Score": 7
        }
      ]
    },
    {
      "name": "Low Risk Preference",
      "description": "Same pool, sorted to show cleanest fundamentals first \u2014 Low risk stocks lead",
      "summary": {
        "Total_Invested": 42736.61,
        "Total_Net_Profit": 5226.55,
        "Portfolio_ROI_%": 12.23,
        "Earliest_Sell": "05 Jan 2028",
        "Latest_Sell": "29 Feb 2028",
        "Num_Stocks": 5,
        "Risk_Breakdown": {
          "Low": 5
        }
      },
      "portfolio": [
        {
          "Stock": "GPIL.NS",
          "Company_Name": "Godawari Power & Ispat Limited",
          "Band": "\u20b90\u2013\u20b9500",
          "Buy_Price": 242.95,
          "Shares": 40,
          "Invested": 9772.2,
          "Exit_Target": 297.35,
          "Exit_Value": 11894.0,
          "Gross_Profit": 2176.0,
          "Net_Profit": 2034.77,
          "Net_ROI_%": 20.82,
          "Best_Sell_Date": "05 Jan 2028",
          "Forecast_Expires": "05 Jan 2028",
          "Predicted_Best_Buy_Date": "20 Jul 2026",
          "Predicted_Best_Buy_Price": 239.19,
          "Turnover_Cr": 28.43,
          "Fundamental_Risk": "Low",
          "Risk_Score": 7
        },
        {
          "Stock": "AUROPHARMA.NS",
          "Company_Name": "Aurobindo Pharma Limited",
          "Band": "\u20b91500\u2013\u20b92000",
          "Buy_Price": 1535.6,
          "Shares": 5,
          "Invested": 7720.23,
          "Exit_Target": 1693.08,
          "Exit_Value": 8465.4,
          "Gross_Profit": 787.4,
          "Net_Profit": 682.47,
          "Net_ROI_%": 8.84,
          "Best_Sell_Date": "25 Nov 2027",
          "Forecast_Expires": "07 Dec 2027",
          "Predicted_Best_Buy_Date": "23 Jul 2026",
          "Predicted_Best_Buy_Price": 1537.04,
          "Turnover_Cr": 210.36,
          "Fundamental_Risk": "Low",
          "Risk_Score": 9
        },
        {
          "Stock": "HINDCOPPER.NS",
          "Company_Name": "Hindustan Copper Limited",
          "Band": "\u20b90\u2013\u20b9500",
          "Buy_Price": 481.85,
          "Shares": 18,
          "Invested": 8721.0,
          "Exit_Target": 534.68,
          "Exit_Value": 9624.24,
          "Gross_Profit": 950.94,
          "Net_Profit": 832.01,
          "Net_ROI_%": 9.54,
          "Best_Sell_Date": "15 Jul 2027",
          "Forecast_Expires": "06 Sep 2027",
          "Predicted_Best_Buy_Date": "25 Aug 2026",
          "Predicted_Best_Buy_Price": 480.32,
          "Turnover_Cr": 157.71,
          "Fundamental_Risk": "Low",
          "Risk_Score": 16
        },
        {
          "Stock": "IKS.NS",
          "Company_Name": "INVENTURUS KNOWLEDGE SO L",
          "Band": "\u20b91500\u2013\u20b92000",
          "Buy_Price": 1876.1,
          "Shares": 4,
          "Invested": 7545.67,
          "Exit_Target": 2080.01,
          "Exit_Value": 8320.04,
          "Gross_Profit": 815.64,
          "Net_Profit": 712.78,
          "Net_ROI_%": 9.45,
          "Best_Sell_Date": "29 Feb 2028",
          "Forecast_Expires": "22 Jun 2028",
          "Predicted_Best_Buy_Date": "14 Aug 2026",
          "Predicted_Best_Buy_Price": 1859.05,
          "Turnover_Cr": 55.83,
          "Fundamental_Risk": "Low",
          "Risk_Score": 7
        },
        {
          "Stock": "JINDALSAW.NS",
          "Company_Name": "Jindal Saw Limited",
          "Band": "\u20b90\u2013\u20b9500",
          "Buy_Price": 262.6,
          "Shares": 34,
          "Invested": 8977.51,
          "Exit_Target": 294.59,
          "Exit_Value": 10016.06,
          "Gross_Profit": 1087.66,
          "Net_Profit": 964.52,
          "Net_ROI_%": 10.74,
          "Best_Sell_Date": "20 Jun 2028",
          "Forecast_Expires": "22 Jun 2028",
          "Predicted_Best_Buy_Date": "22 Jul 2026",
          "Predicted_Best_Buy_Price": 261.87,
          "Turnover_Cr": 47.09,
          "Fundamental_Risk": "Low",
          "Risk_Score": 9
        }
      ]
    }
  ],
  "full_pool": [
    {
      "Price_Band": "\u20b90\u2013\u20b9500",
      "Stock": "GPIL.NS",
      "Company_Name": "Godawari Power & Ispat Limited",
      "Buy_Price": 242.95,
      "Exit_Target": 297.35,
      "Gross_ROI_%": 19.99,
      "After_Tax_ROI_%": 19.77,
      "Tax_Type": "LTCG",
      "Min_Hold_Until": "06 Jul 2027",
      "Best_Sell_Date": "05 Jan 2028",
      "Forecast_Expires": "05 Jan 2028",
      "Avg_Daily_Turnover_Cr": 28.43,
      "Sector": "Basic Materials",
      "Liquidity": "High",
      "Data_Days": 743,
      "Predicted_Best_Buy_Date": "20 Jul 2026",
      "Predicted_Best_Buy_Price": 239.19,
      "Fundamental_Risk": "Low",
      "Risk_Score": 7,
      "Risk_Reasons": "PE=19.3 within limit=55 (1.0\u00d7); D/E=0.08 within limit=3.25 (1.0\u00d7); Revenue growth=9.7% \u2192 0.90\u00d7; All 3 fields present (1.0\u00d7); ROE=14.9% \u2014 adequate (1.0\u00d7); EV/EBITDA=11.5x within limit=22x (1.0\u00d7); Earnings quality=1.45 \u2014 adequate (1.0\u00d7); Net Debt/EBITDA=-0.6x \u2014 net cash position (0.95\u00d7)"
    },
    {
      "Price_Band": "\u20b9500\u2013\u20b91000",
      "Stock": "NATCOPHARM.NS",
      "Company_Name": "NATCO Pharma Limited",
      "Buy_Price": 948.4,
      "Exit_Target": 1147.01,
      "Gross_ROI_%": 18.57,
      "After_Tax_ROI_%": 18.35,
      "Tax_Type": "LTCG",
      "Min_Hold_Until": "06 Jul 2027",
      "Best_Sell_Date": "20 Oct 2027",
      "Forecast_Expires": "20 Oct 2027",
      "Avg_Daily_Turnover_Cr": 57.31,
      "Sector": "Healthcare",
      "Liquidity": "High",
      "Data_Days": 744,
      "Predicted_Best_Buy_Date": "30 Jul 2026",
      "Predicted_Best_Buy_Price": 945.32,
      "Fundamental_Risk": "Medium",
      "Risk_Score": 38,
      "Risk_Reasons": "PE=12.0 within limit=50 (1.0\u00d7); D/E=0.08 within limit=2.75 (1.0\u00d7); Revenue growth=-39.6% \u2192 2.20\u00d7; All 3 fields present (1.0\u00d7); ROE=16.9% \u2014 adequate (1.0\u00d7); EV/EBITDA=11.1x within limit=25x (1.0\u00d7); Earnings quality=1.25 \u2014 adequate (1.0\u00d7); Net Debt/EBITDA=-1.0x \u2014 net cash position (0.95\u00d7)"
    },
    {
      "Price_Band": "\u20b90\u2013\u20b9500",
      "Stock": "TMCV.NS",
      "Company_Name": "TATA MOTORS LIMITED",
      "Buy_Price": 415.15,
      "Exit_Target": 475.41,
      "Gross_ROI_%": 12.27,
      "After_Tax_ROI_%": 12.06,
      "Tax_Type": "LTCG",
      "Min_Hold_Until": "06 Jul 2027",
      "Best_Sell_Date": "25 Oct 2027",
      "Forecast_Expires": "25 Oct 2027",
      "Avg_Daily_Turnover_Cr": 331.16,
      "Sector": "Consumer Cyclical",
      "Liquidity": "High",
      "Data_Days": 171,
      "Predicted_Best_Buy_Date": "23 Jul 2026",
      "Predicted_Best_Buy_Price": 413.54,
      "Fundamental_Risk": "High",
      "Risk_Score": 84,
      "Risk_Reasons": "PE=51.9 vs limit=25 \u2192 2.08\u00d7 (4.00\u00d7); D/E=0.44 within limit=2.55 (1.0\u00d7); Revenue growth=-37.8% \u2192 2.20\u00d7; All 3 fields present (1.0\u00d7); ROE=26.0% \u2014 strong (0.90\u00d7); EV/EBITDA=17.0x within limit=18x (1.0\u00d7); Earnings quality=4.94 \u2014 adequate (1.0\u00d7); Net Debt/EBITDA=-0.9x \u2014 net cash position (0.95\u00d7)"
    },
    {
      "Price_Band": "\u20b90\u2013\u20b9500",
      "Stock": "JINDALSAW.NS",
      "Company_Name": "Jindal Saw Limited",
      "Buy_Price": 262.6,
      "Exit_Target": 294.59,
      "Gross_ROI_%": 9.98,
      "After_Tax_ROI_%": 9.77,
      "Tax_Type": "LTCG",
      "Min_Hold_Until": "06 Jul 2027",
      "Best_Sell_Date": "20 Jun 2028",
      "Forecast_Expires": "22 Jun 2028",
      "Avg_Daily_Turnover_Cr": 47.09,
      "Sector": "Basic Materials",
      "Liquidity": "High",
      "Data_Days": 743,
      "Predicted_Best_Buy_Date": "22 Jul 2026",
      "Predicted_Best_Buy_Price": 261.87,
      "Fundamental_Risk": "Low",
      "Risk_Score": 9,
      "Risk_Reasons": "PE=25.7 within limit=55 (1.0\u00d7); D/E=0.38 within limit=3.25 (1.0\u00d7); Revenue growth=9.0% \u2192 0.91\u00d7; All 3 fields present (1.0\u00d7); ROE unavailable \u2014 no multiplier; EV/EBITDA=11.1x within limit=22x (1.0\u00d7); Earnings quality unavailable \u2014 no multiplier; Net Debt/EBITDA=2.2x within limit=3.5x (1.0\u00d7)"
    },
    {
      "Price_Band": "\u20b90\u2013\u20b9500",
      "Stock": "NLCINDIA.NS",
      "Company_Name": "NLC India Limited",
      "Buy_Price": 296.2,
      "Exit_Target": 329.83,
      "Gross_ROI_%": 9.17,
      "After_Tax_ROI_%": 8.96,
      "Tax_Type": "LTCG",
      "Min_Hold_Until": "06 Jul 2027",
      "Best_Sell_Date": "24 May 2028",
      "Forecast_Expires": "22 Jun 2028",
      "Avg_Daily_Turnover_Cr": 94.07,
      "Sector": "Utilities",
      "Liquidity": "High",
      "Data_Days": 743,
      "Predicted_Best_Buy_Date": "24 Jul 2026",
      "Predicted_Best_Buy_Price": 296.59,
      "Fundamental_Risk": "Low",
      "Risk_Score": 13,
      "Risk_Reasons": "PE=11.7 within limit=38 (1.0\u00d7); D/E=0.82 within limit=5.5 (1.0\u00d7); Revenue growth=-0.3% \u2192 1.01\u00d7; All 3 fields present (1.0\u00d7); ROE=16.0% \u2014 acceptable for utility (1.0\u00d7); EV/EBITDA=9.6x within limit=22x (1.0\u00d7); Earnings quality=1.47 \u2014 adequate (1.0\u00d7); Net Debt/EBITDA=2.0x within limit=6.0x (1.0\u00d7)"
    },
    {
      "Price_Band": "\u20b90\u2013\u20b9500",
      "Stock": "MAHABANK.NS",
      "Company_Name": "Bank of Maharashtra",
      "Buy_Price": 79.56,
      "Exit_Target": 88.45,
      "Gross_ROI_%": 8.99,
      "After_Tax_ROI_%": 8.78,
      "Tax_Type": "LTCG",
      "Min_Hold_Until": "06 Jul 2027",
      "Best_Sell_Date": "01 May 2028",
      "Forecast_Expires": "22 Jun 2028",
      "Avg_Daily_Turnover_Cr": 163.42,
      "Sector": "Financial Services",
      "Liquidity": "High",
      "Data_Days": 743,
      "Predicted_Best_Buy_Date": "20 Jul 2026",
      "Predicted_Best_Buy_Price": 79.6,
      "Fundamental_Risk": "Low",
      "Risk_Score": 13,
      "Risk_Reasons": "PE=8.1 within limit=22 (1.0\u00d7); D/E exempt \u2014 financial sector (1.0\u00d7); Revenue growth=21.8% \u2192 0.85\u00d7; 1 field(s) missing \u2192 1.2\u00d7; ROE=23.0% \u2014 acceptable (1.0\u00d7); EV/EBITDA unavailable \u2014 no multiplier; Earnings quality unavailable \u2014 no multiplier; Net Debt/EBITDA unavailable \u2014 no multiplier"
    },
    {
      "Price_Band": "\u20b90\u2013\u20b9500",
      "Stock": "IFCI.NS",
      "Company_Name": "IFCI Limited",
      "Buy_Price": 71.66,
      "Exit_Target": 79.54,
      "Gross_ROI_%": 8.81,
      "After_Tax_ROI_%": 8.6,
      "Tax_Type": "LTCG",
      "Min_Hold_Until": "06 Jul 2027",
      "Best_Sell_Date": "14 Feb 2028",
      "Forecast_Expires": "21 Mar 2028",
      "Avg_Daily_Turnover_Cr": 242.21,
      "Sector": "Financial Services",
      "Liquidity": "High",
      "Data_Days": 744,
      "Predicted_Best_Buy_Date": "29 Jul 2026",
      "Predicted_Best_Buy_Price": 71.55,
      "Fundamental_Risk": "High",
      "Risk_Score": 76,
      "Risk_Reasons": "PE=105.4 vs limit=45 \u2192 2.34\u00d7 (4.00\u00d7); D/E exempt \u2014 financial sector (1.0\u00d7); Revenue growth unavailable \u2014 no multiplier; 2 field(s) missing \u2192 1.5\u00d7; ROE unavailable \u2014 no multiplier; EV/EBITDA unavailable \u2014 no multiplier; Earnings quality unavailable \u2014 no multiplier; Net Debt/EBITDA unavailable \u2014 no multiplier"
    },
    {
      "Price_Band": "\u20b90\u2013\u20b9500",
      "Stock": "HINDCOPPER.NS",
      "Company_Name": "Hindustan Copper Limited",
      "Buy_Price": 481.85,
      "Exit_Target": 534.68,
      "Gross_ROI_%": 8.79,
      "After_Tax_ROI_%": 8.58,
      "Tax_Type": "LTCG",
      "Min_Hold_Until": "06 Jul 2027",
      "Best_Sell_Date": "15 Jul 2027",
      "Forecast_Expires": "06 Sep 2027",
      "Avg_Daily_Turnover_Cr": 157.71,
      "Sector": "Basic Materials",
      "Liquidity": "High",
      "Data_Days": 744,
      "Predicted_Best_Buy_Date": "25 Aug 2026",
      "Predicted_Best_Buy_Price": 480.32,
      "Fundamental_Risk": "Low",
      "Risk_Score": 16,
      "Risk_Reasons": "PE=51.5 within limit=55 (1.0\u00d7); D/E=0.03 within limit=3.25 (1.0\u00d7); Revenue growth=58.1% \u2192 0.85\u00d7; All 3 fields present (1.0\u00d7); ROE=30.6% \u2014 strong (0.90\u00d7); EV/EBITDA=31.6x vs limit=22x (1.51\u00d7); Earnings quality=1.60 \u2014 adequate (1.0\u00d7); Net Debt/EBITDA=-0.5x \u2014 net cash position (0.95\u00d7)"
    },
    {
      "Price_Band": "\u20b91500\u2013\u20b92000",
      "Stock": "IKS.NS",
      "Company_Name": "INVENTURUS KNOWLEDGE SO L",
      "Buy_Price": 1876.1,
      "Exit_Target": 2080.01,
      "Gross_ROI_%": 8.69,
      "After_Tax_ROI_%": 8.49,
      "Tax_Type": "LTCG",
      "Min_Hold_Until": "06 Jul 2027",
      "Best_Sell_Date": "29 Feb 2028",
      "Forecast_Expires": "22 Jun 2028",
      "Avg_Daily_Turnover_Cr": 55.83,
      "Sector": "Healthcare",
      "Liquidity": "High",
      "Data_Days": 391,
      "Predicted_Best_Buy_Date": "14 Aug 2026",
      "Predicted_Best_Buy_Price": 1859.05,
      "Fundamental_Risk": "Low",
      "Risk_Score": 7,
      "Risk_Reasons": "PE=44.4 within limit=76 (1.0\u00d7); D/E=0.27 within limit=2.75 (1.0\u00d7); Revenue growth=18.5% \u2192 0.85\u00d7; All 3 fields present (1.0\u00d7); ROE=31.4% \u2014 strong (0.90\u00d7); EV/EBITDA=28.7x vs limit=25x (1.13\u00d7); Earnings quality=0.93 \u2014 adequate (1.0\u00d7); Net Debt/EBITDA=0.1x within limit=3.5x (1.0\u00d7)"
    },
    {
      "Price_Band": "\u20b97000\u2013\u20b915000",
      "Stock": "POLYCAB.NS",
      "Company_Name": "Polycab India Limited",
      "Buy_Price": 8873.0,
      "Exit_Target": 9836.91,
      "Gross_ROI_%": 8.69,
      "After_Tax_ROI_%": 8.48,
      "Tax_Type": "LTCG",
      "Min_Hold_Until": "06 Jul 2027",
      "Best_Sell_Date": "21 Jun 2028",
      "Forecast_Expires": "22 Jun 2028",
      "Avg_Daily_Turnover_Cr": 369.21,
      "Sector": "Industrials",
      "Liquidity": "High",
      "Data_Days": 744,
      "Predicted_Best_Buy_Date": "29 Jul 2026",
      "Predicted_Best_Buy_Price": 8870.4,
      "Fundamental_Risk": "Low",
      "Risk_Score": 18,
      "Risk_Reasons": "PE=50.7 within limit=60 (1.0\u00d7); D/E=0.03 within limit=3.5 (1.0\u00d7); Revenue growth=26.9% \u2192 0.85\u00d7; All 3 fields present (1.0\u00d7); ROE=24.6% \u2014 strong (0.90\u00d7); EV/EBITDA=33.2x vs limit=22x (1.62\u00d7); Earnings quality=1.43 \u2014 adequate (1.0\u00d7); Net Debt/EBITDA=-0.9x \u2014 net cash position (0.95\u00d7)"
    },
    {
      "Price_Band": "\u20b97000\u2013\u20b915000",
      "Stock": "OFSS.NS",
      "Company_Name": "Oracle Financial Services Software Limited",
      "Buy_Price": 11619.0,
      "Exit_Target": 12849.37,
      "Gross_ROI_%": 8.42,
      "After_Tax_ROI_%": 8.21,
      "Tax_Type": "LTCG",
      "Min_Hold_Until": "06 Jul 2027",
      "Best_Sell_Date": "20 Jan 2028",
      "Forecast_Expires": "20 Jan 2028",
      "Avg_Daily_Turnover_Cr": 359.3,
      "Sector": "Technology",
      "Liquidity": "High",
      "Data_Days": 743,
      "Predicted_Best_Buy_Date": "20 Jul 2026",
      "Predicted_Best_Buy_Price": 11612.21,
      "Fundamental_Risk": "Low",
      "Risk_Score": 1,
      "Risk_Reasons": "PE=38.4 within limit=65 (1.0\u00d7); D/E=0.00 within limit=2.0 (1.0\u00d7); Revenue growth=20.3% \u2192 0.85\u00d7; All 3 fields present (1.0\u00d7); ROE=32.6% \u2014 strong (0.90\u00d7); EV/EBITDA=27.8x within limit=30x (1.0\u00d7); Earnings quality=1.00 \u2014 adequate (1.0\u00d7); Net Debt/EBITDA=-1.6x \u2014 net cash position (0.95\u00d7)"
    },
    {
      "Price_Band": "\u20b91500\u2013\u20b92000",
      "Stock": "AUROPHARMA.NS",
      "Company_Name": "Aurobindo Pharma Limited",
      "Buy_Price": 1535.6,
      "Exit_Target": 1693.08,
      "Gross_ROI_%": 8.09,
      "After_Tax_ROI_%": 7.89,
      "Tax_Type": "LTCG",
      "Min_Hold_Until": "06 Jul 2027",
      "Best_Sell_Date": "25 Nov 2027",
      "Forecast_Expires": "07 Dec 2027",
      "Avg_Daily_Turnover_Cr": 210.36,
      "Sector": "Healthcare",
      "Liquidity": "High",
      "Data_Days": 742,
      "Predicted_Best_Buy_Date": "23 Jul 2026",
      "Predicted_Best_Buy_Price": 1537.04,
      "Fundamental_Risk": "Low",
      "Risk_Score": 9,
      "Risk_Reasons": "PE=25.5 within limit=50 (1.0\u00d7); D/E=0.21 within limit=2.75 (1.0\u00d7); Revenue growth=5.6% \u2192 0.94\u00d7; All 3 fields present (1.0\u00d7); ROE=9.9% \u2014 poor capital allocation (1.00\u00d7); EV/EBITDA=12.7x within limit=25x (1.0\u00d7); Earnings quality=1.58 \u2014 adequate (1.0\u00d7); Net Debt/EBITDA=-0.4x \u2014 net cash position (0.95\u00d7)"
    },
    {
      "Price_Band": "\u20b90\u2013\u20b9500",
      "Stock": "NATIONALUM.NS",
      "Company_Name": "National Aluminium Company Limited",
      "Buy_Price": 341.05,
      "Exit_Target": 375.84,
      "Gross_ROI_%": 8.04,
      "After_Tax_ROI_%": 7.83,
      "Tax_Type": "LTCG",
      "Min_Hold_Until": "06 Jul 2027",
      "Best_Sell_Date": "07 Apr 2028",
      "Forecast_Expires": "28 Apr 2028",
      "Avg_Daily_Turnover_Cr": 389.08,
      "Sector": "Basic Materials",
      "Liquidity": "High",
      "Data_Days": 743,
      "Predicted_Best_Buy_Date": "24 Jul 2026",
      "Predicted_Best_Buy_Price": 340.76,
      "Fundamental_Risk": "Low",
      "Risk_Score": 16,
      "Risk_Reasons": "PE=10.2 within limit=55 (1.0\u00d7); D/E=0.00 within limit=3.25 (1.0\u00d7); Revenue growth=-4.8% \u2192 1.31\u00d7; All 3 fields present (1.0\u00d7); ROE=29.4% \u2014 strong (0.90\u00d7); EV/EBITDA=7.1x within limit=22x (1.0\u00d7); Earnings quality=1.11 \u2014 adequate (1.0\u00d7); Net Debt/EBITDA=-1.1x \u2014 net cash position (0.95\u00d7)"
    },
    {
      "Price_Band": "\u20b90\u2013\u20b9500",
      "Stock": "SARDAEN.NS",
      "Company_Name": "Sarda Energy & Minerals Limited",
      "Buy_Price": 492.85,
      "Exit_Target": 542.36,
      "Gross_ROI_%": 7.89,
      "After_Tax_ROI_%": 7.68,
      "Tax_Type": "LTCG",
      "Min_Hold_Until": "06 Jul 2027",
      "Best_Sell_Date": "19 May 2028",
      "Forecast_Expires": "22 Jun 2028",
      "Avg_Daily_Turnover_Cr": 12.62,
      "Sector": "Basic Materials",
      "Liquidity": "High",
      "Data_Days": 743,
      "Predicted_Best_Buy_Date": "20 Jul 2026",
      "Predicted_Best_Buy_Price": 494.19,
      "Fundamental_Risk": "Low",
      "Risk_Score": 13,
      "Risk_Reasons": "PE=15.7 within limit=55 (1.0\u00d7); D/E=0.35 within limit=3.25 (1.0\u00d7); Revenue growth=-0.6% \u2192 1.03\u00d7; All 3 fields present (1.0\u00d7); ROE=16.0% \u2014 adequate (1.0\u00d7); EV/EBITDA=10.0x within limit=22x (1.0\u00d7); Earnings quality=1.57 \u2014 adequate (1.0\u00d7); Net Debt/EBITDA=0.1x within limit=3.5x (1.0\u00d7)"
    }
  ]
}